<?xml version='1.0' encoding='UTF-8'?>
<mnemosyne core_version='1'>
<category active='1'>
<name>Langara - This Summer - English</name>
</category>
<category active='1'>
<name>Langara - This Summer - Hanzi</name>
</category>
<category active='1'>
<name>Langara - This Summer - Traditional</name>
</category>
<category active='1'>
<name>Langara - This Summer - Pinyin</name>
</category>
<category active='1'>
<name>Langara - This Summer - Words</name>
</category>
<item id='_0'>
<cat>Langara - This Summer - English</cat>
<Q>Write the character:&lt;br&gt;1: kind&lt;br&gt;2: to plant; to cultivate</Q>
<A>&lt;img src="stroke-images/0144.png"&gt;&lt;br&gt;traditional: 種&lt;br&gt;1: zhǒng 2: zhòng&lt;br&gt;这种 (這種) zhèzhǒng this; this kind of; this sort of; this type of 种植 (種植) zhòngzhí plant; grow</A>
</item>
<item id='_1'>
<cat>Langara - This Summer - English</cat>
<Q>Write the character:&lt;br&gt;hand; convenient</Q>
<A>&lt;img src="stroke-images/0151.png"&gt;&lt;br&gt;shǒu&lt;br&gt;手段 shǒuduàn method; mean (of doing sth)</A>
</item>
<item id='_2'>
<cat>Langara - This Summer - English</cat>
<Q>Write the character:&lt;br&gt;already; to stop; then; afterwards</Q>
<A>&lt;img src="stroke-images/0153.png"&gt;&lt;br&gt;yǐ&lt;br&gt;已经 (已經) yǐjīng already</A>
</item>
<item id='_3'>
<cat>Langara - This Summer - English</cat>
<Q>Write the character:&lt;br&gt;clear; bright; to understand; next; the Ming dynasty (1368- 1644); surname</Q>
<A>&lt;img src="stroke-images/0154.png"&gt;&lt;br&gt;míng&lt;br&gt;说明 (說明) shuōmíng to explain; to illustrate; explanation; directions; caption</A>
</item>
<item id='_4'>
<cat>Langara - This Summer - English</cat>
<Q>Write the character:&lt;br&gt;to beat; to strike; to hit; to break; to type; to mix up; to build; to fight; to fetch; to make; to tie up; to issue; to shoot; to calculate; since; from</Q>
<A>&lt;img src="stroke-images/0155.png"&gt;&lt;br&gt;dǎ&lt;br&gt;打击 (打擊) dǎjī to hit; to strike; to attack</A>
</item>
<item id='_5'>
<cat>Langara - This Summer - English</cat>
<Q>Write the character:&lt;br&gt;highest; greatest; too (much); very; extremely</Q>
<A>&lt;img src="stroke-images/0156.png"&gt;&lt;br&gt;tài&lt;br&gt;太太 tàitai married woman; Mrs.; Madam; wife</A>
</item>
<item id='_6'>
<cat>Langara - This Summer - English</cat>
<Q>Write the character:&lt;br&gt;outside; in addition; foreign; external</Q>
<A>&lt;img src="stroke-images/0166.png"&gt;&lt;br&gt;wài&lt;br&gt;外国 (外國) wàiguó foreign (country)</A>
</item>
<item id='_7'>
<cat>Langara - This Summer - English</cat>
<Q>Write the character:&lt;br&gt;each; every</Q>
<A>&lt;img src="stroke-images/0178.png"&gt;&lt;br&gt;gè&lt;br&gt;各个 (各個) gège various</A>
</item>
<item id='_8'>
<cat>Langara - This Summer - English</cat>
<Q>Write the character:&lt;br&gt;1: (will, shall, "future tense"); ready; prepared; to get; to use&lt;br&gt;2: a general</Q>
<A>&lt;img src="stroke-images/0180.png"&gt;&lt;br&gt;traditional: 將&lt;br&gt;1: jiāng 2: jiàng&lt;br&gt;将来 (將來) jiānglái (the) future 将领 (將領) jiànglǐng high-ranking military officer</A>
</item>
<item id='_9'>
<cat>Langara - This Summer - English</cat>
<Q>Write the character:&lt;br&gt;1: few; little; lack&lt;br&gt;2: young</Q>
<A>&lt;img src="stroke-images/0181.png"&gt;&lt;br&gt;1: shǎo 2: shào&lt;br&gt;减少 (減少) jiǎnshǎo to lessen; to decrease; to reduce; to lower 少年 shàonián juvenile; youngster</A>
</item>
<item id='_10'>
<cat>Langara - This Summer - Hanzi</cat>
<Q>种</Q>
<A>traditional: 種&lt;br&gt;1: zhǒng 2: zhòng&lt;br&gt;1: kind&lt;br&gt;2: to plant; to cultivate&lt;br&gt;这种 (這種) zhèzhǒng this; this kind of; this sort of; this type of 种植 (種植) zhòngzhí plant; grow</A>
</item>
<item id='_11'>
<cat>Langara - This Summer - Hanzi</cat>
<Q>手</Q>
<A>shǒu&lt;br&gt;hand; convenient&lt;br&gt;手段 shǒuduàn method; mean (of doing sth)</A>
</item>
<item id='_12'>
<cat>Langara - This Summer - Hanzi</cat>
<Q>已</Q>
<A>yǐ&lt;br&gt;already; to stop; then; afterwards&lt;br&gt;已经 (已經) yǐjīng already</A>
</item>
<item id='_13'>
<cat>Langara - This Summer - Hanzi</cat>
<Q>明</Q>
<A>míng&lt;br&gt;clear; bright; to understand; next; the Ming dynasty (1368- 1644); surname Ming&lt;br&gt;说明 (說明) shuōmíng to explain; to illustrate; explanation; directions; caption</A>
</item>
<item id='_14'>
<cat>Langara - This Summer - Hanzi</cat>
<Q>打</Q>
<A>dǎ&lt;br&gt;to beat; to strike; to hit; to break; to type; to mix up; to build; to fight; to fetch; to make; to tie up; to issue; to shoot; to calculate; since; from&lt;br&gt;打击 (打擊) dǎjī to hit; to strike; to attack</A>
</item>
<item id='_15'>
<cat>Langara - This Summer - Hanzi</cat>
<Q>太</Q>
<A>tài&lt;br&gt;highest; greatest; too (much); very; extremely&lt;br&gt;太太 tàitai married woman; Mrs.; Madam; wife</A>
</item>
<item id='_16'>
<cat>Langara - This Summer - Hanzi</cat>
<Q>外</Q>
<A>wài&lt;br&gt;outside; in addition; foreign; external&lt;br&gt;外国 (外國) wàiguó foreign (country)</A>
</item>
<item id='_17'>
<cat>Langara - This Summer - Hanzi</cat>
<Q>各</Q>
<A>gè&lt;br&gt;each; every&lt;br&gt;各个 (各個) gège various</A>
</item>
<item id='_18'>
<cat>Langara - This Summer - Hanzi</cat>
<Q>将</Q>
<A>traditional: 將&lt;br&gt;1: jiāng 2: jiàng&lt;br&gt;1: (will, shall, "future tense"); ready; prepared; to get; to use&lt;br&gt;2: a general&lt;br&gt;将来 (將來) jiānglái (the) future 将领 (將領) jiànglǐng high-ranking military officer</A>
</item>
<item id='_19'>
<cat>Langara - This Summer - Hanzi</cat>
<Q>少</Q>
<A>1: shǎo 2: shào&lt;br&gt;1: few; little; lack&lt;br&gt;2: young&lt;br&gt;减少 (減少) jiǎnshǎo to lessen; to decrease; to reduce; to lower 少年 shàonián juvenile; youngster</A>
</item>
<item id='_20'>
<cat>Langara - This Summer - Traditional</cat>
<Q>種</Q>
<A>simplified: 种&lt;br&gt;1: zhǒng 2: zhòng&lt;br&gt;1: kind&lt;br&gt;2: to plant; to cultivate&lt;br&gt;这种 (這種) zhèzhǒng this; this kind of; this sort of; this type of 种植 (種植) zhòngzhí plant; grow</A>
</item>
<item id='_21'>
<cat>Langara - This Summer - Traditional</cat>
<Q>將</Q>
<A>simplified: 将&lt;br&gt;1: jiāng 2: jiàng&lt;br&gt;1: (will, shall, "future tense"); ready; prepared; to get; to use&lt;br&gt;2: a general&lt;br&gt;将来 (將來) jiānglái (the) future 将领 (將領) jiànglǐng high-ranking military officer</A>
</item>
<item id='_22'>
<cat>Langara - This Summer - Pinyin</cat>
<Q>Write the character: zhǒng&lt;br&gt;(zhèzhǒng de zhǒng)</Q>
<A>&lt;img src="stroke-images/0144.png"&gt;&lt;br&gt;traditional: 種&lt;br&gt;kind&lt;br&gt;这种 (這種) zhèzhǒng this; this kind of; this sort of; this type of</A>
</item>
<item id='_23'>
<cat>Langara - This Summer - Pinyin</cat>
<Q>Write the character: zhòng&lt;br&gt;(zhòngzhí de zhòng)</Q>
<A>&lt;img src="stroke-images/0144.png"&gt;&lt;br&gt;traditional: 種&lt;br&gt;to plant; to cultivate&lt;br&gt;种植 (種植) zhòngzhí plant; grow</A>
</item>
<item id='_24'>
<cat>Langara - This Summer - Pinyin</cat>
<Q>Write the character: shǒu&lt;br&gt;(shǒuduàn de shǒu)</Q>
<A>&lt;img src="stroke-images/0151.png"&gt;&lt;br&gt;hand; convenient&lt;br&gt;手段 shǒuduàn method; mean (of doing sth)</A>
</item>
<item id='_25'>
<cat>Langara - This Summer - Pinyin</cat>
<Q>Write the character: yǐ&lt;br&gt;(yǐjīng de yǐ)</Q>
<A>&lt;img src="stroke-images/0153.png"&gt;&lt;br&gt;already; to stop; then; afterwards&lt;br&gt;已经 (已經) yǐjīng already</A>
</item>
<item id='_26'>
<cat>Langara - This Summer - Pinyin</cat>
<Q>Write the character: míng&lt;br&gt;(shuōmíng de míng)</Q>
<A>&lt;img src="stroke-images/0154.png"&gt;&lt;br&gt;clear; bright; to understand; next; the Ming dynasty (1368- 1644); surname Ming&lt;br&gt;说明 (說明) shuōmíng to explain; to illustrate; explanation; directions; caption</A>
</item>
<item id='_27'>
<cat>Langara - This Summer - Pinyin</cat>
<Q>Write the character: dǎ&lt;br&gt;(dǎjī de dǎ)</Q>
<A>&lt;img src="stroke-images/0155.png"&gt;&lt;br&gt;to beat; to strike; to hit; to break; to type; to mix up; to build; to fight; to fetch; to make; to tie up; to issue; to shoot; to calculate; since; from&lt;br&gt;打击 (打擊) dǎjī to hit; to strike; to attack</A>
</item>
<item id='_28'>
<cat>Langara - This Summer - Pinyin</cat>
<Q>Write the character: tài&lt;br&gt;(tàitai de tài)</Q>
<A>&lt;img src="stroke-images/0156.png"&gt;&lt;br&gt;highest; greatest; too (much); very; extremely&lt;br&gt;太太 tàitai married woman; Mrs.; Madam; wife</A>
</item>
<item id='_29'>
<cat>Langara - This Summer - Pinyin</cat>
<Q>Write the character: wài&lt;br&gt;(wàiguó de wài)</Q>
<A>&lt;img src="stroke-images/0166.png"&gt;&lt;br&gt;outside; in addition; foreign; external&lt;br&gt;外国 (外國) wàiguó foreign (country)</A>
</item>
<item id='_30'>
<cat>Langara - This Summer - Pinyin</cat>
<Q>Write the character: gè&lt;br&gt;(gège de gè)</Q>
<A>&lt;img src="stroke-images/0178.png"&gt;&lt;br&gt;each; every&lt;br&gt;各个 (各個) gège various</A>
</item>
<item id='_31'>
<cat>Langara - This Summer - Pinyin</cat>
<Q>Write the character: jiāng&lt;br&gt;(jiānglái de jiāng)</Q>
<A>&lt;img src="stroke-images/0180.png"&gt;&lt;br&gt;traditional: 將&lt;br&gt;(will, shall, "future tense"); ready; prepared; to get; to use&lt;br&gt;将来 (將來) jiānglái (the) future</A>
</item>
<item id='_32'>
<cat>Langara - This Summer - Pinyin</cat>
<Q>Write the character: jiàng&lt;br&gt;(jiànglǐng de jiàng)</Q>
<A>&lt;img src="stroke-images/0180.png"&gt;&lt;br&gt;traditional: 將&lt;br&gt;a general&lt;br&gt;将领 (將領) jiànglǐng high-ranking military officer</A>
</item>
<item id='_33'>
<cat>Langara - This Summer - Pinyin</cat>
<Q>Write the character: shǎo&lt;br&gt;(jiǎnshǎo de shǎo)</Q>
<A>&lt;img src="stroke-images/0181.png"&gt;&lt;br&gt;few; little; lack&lt;br&gt;减少 (減少) jiǎnshǎo to lessen; to decrease; to reduce; to lower</A>
</item>
<item id='_34'>
<cat>Langara - This Summer - Pinyin</cat>
<Q>Write the character: shào&lt;br&gt;(shàonián de shào)</Q>
<A>&lt;img src="stroke-images/0181.png"&gt;&lt;br&gt;young&lt;br&gt;少年 shàonián juvenile; youngster</A>
</item>
</mnemosyne>
