<?xml version='1.0' encoding='UTF-8'?>
<mnemosyne core_version='1'>
<category active='1'>
<name>Most common Chinese characters 2810-2831 - English</name>
</category>
<category active='1'>
<name>Most common Chinese characters 2810-2831 - Hanzi</name>
</category>
<category active='1'>
<name>Most common Chinese characters 2810-2831 - Traditional</name>
</category>
<category active='1'>
<name>Most common Chinese characters 2810-2831 - Pinyin</name>
</category>
<category active='1'>
<name>Most common Chinese characters 2810-2831 - Words</name>
</category>
<item id='_0'>
<cat>Most common Chinese characters 2810-2831 - English</cat>
<Q>Write the character:&lt;br&gt;sleeve of a robe</Q>
<A>袂 (strokes unavailable)&lt;br&gt;mèi</A>
</item>
<item id='_1'>
<cat>Most common Chinese characters 2810-2831 - English</cat>
<Q>Write the character:&lt;br&gt;rigid</Q>
<A>僵 (strokes unavailable)&lt;br&gt;jiāng&lt;br&gt;僵硬 jiāngyìng stark; stiff</A>
</item>
<item id='_2'>
<cat>Most common Chinese characters 2810-2831 - English</cat>
<Q>Write the character:&lt;br&gt;embarrassed; ill at ease</Q>
<A>尴 (strokes unavailable)&lt;br&gt;traditional: 尷&lt;br&gt;gān</A>
</item>
<item id='_3'>
<cat>Most common Chinese characters 2810-2831 - English</cat>
<Q>Write the character:&lt;br&gt;closely joined; connection; knot</Q>
<A>缔 (strokes unavailable)&lt;br&gt;traditional: 締&lt;br&gt;dì&lt;br&gt;缔结 (締結) dìjié (v) conclude (an agreement)</A>
</item>
<item id='_4'>
<cat>Most common Chinese characters 2810-2831 - English</cat>
<Q>Write the character:&lt;br&gt;1: areca; the areca nut palm&lt;br&gt;2: areca</Q>
<A>槟 (strokes unavailable)&lt;br&gt;traditional: 檳&lt;br&gt;1: bīn 2: bīng&lt;br&gt;槟榔 (檳榔) bīnláng areca 槟榔 (檳榔) bīnglang betel palm (Areca catechu); betel nut</A>
</item>
<item id='_5'>
<cat>Most common Chinese characters 2810-2831 - English</cat>
<Q>Write the character:&lt;br&gt;tie with string or ribbon; bind with rope or cord; to stop</Q>
<A>扎 (strokes unavailable)&lt;br&gt;traditional: 紮&lt;br&gt;zā&lt;br&gt;包扎 (包紮) bāozā to bind; to wrap up; to bind up; to pack</A>
</item>
<item id='_6'>
<cat>Most common Chinese characters 2810-2831 - English</cat>
<Q>Write the character:&lt;br&gt;hatchet</Q>
<A>斧 (strokes unavailable)&lt;br&gt;fǔ&lt;br&gt;斧头 (斧頭) fǔtóu ax; hatchet</A>
</item>
<item id='_7'>
<cat>Most common Chinese characters 2810-2831 - English</cat>
<Q>Write the character:&lt;br&gt;lapel; overlap of Chinese gown; fig. bosom (the seat of emotions); to cherish (ambition, desires, honorable intentions etc) in one's bosom</Q>
<A>襟 (strokes unavailable)&lt;br&gt;jīn&lt;br&gt;胸襟 xiōngjīn lapel of jacket; heart; aspiration; vision</A>
</item>
<item id='_8'>
<cat>Most common Chinese characters 2810-2831 - English</cat>
<Q>Write the character:&lt;br&gt;have jurisdiction over; linchpin of a wheel (archaic)</Q>
<A>辖 (strokes unavailable)&lt;br&gt;traditional: 轄&lt;br&gt;xía&lt;br&gt;管辖 (管轄) guǎnxía administer; have jurisdiction (over)</A>
</item>
<item id='_9'>
<cat>Most common Chinese characters 2810-2831 - English</cat>
<Q>Write the character:&lt;br&gt;similar; resembling; to resemble; to be like</Q>
<A>肖 (strokes unavailable)&lt;br&gt;xiào&lt;br&gt;肖像 xiàoxiàng portrait</A>
</item>
<item id='_10'>
<cat>Most common Chinese characters 2810-2831 - English</cat>
<Q>Write the character:&lt;br&gt;blunt; stupid</Q>
<A>钝 (strokes unavailable)&lt;br&gt;traditional: 鈍&lt;br&gt;dùn&lt;br&gt;钝角 (鈍角) dùnjǐa obtuse angle</A>
</item>
<item id='_11'>
<cat>Most common Chinese characters 2810-2831 - English</cat>
<Q>Write the character:&lt;br&gt;swollen</Q>
<A>肿 (strokes unavailable)&lt;br&gt;traditional: 腫&lt;br&gt;zhǒng&lt;br&gt;水肿 (水腫) shuǐzhǒng (med.) edema; dropsy</A>
</item>
<item id='_12'>
<cat>Most common Chinese characters 2810-2831 - English</cat>
<Q>Write the character:&lt;br&gt;lemon</Q>
<A>檬 (strokes unavailable)&lt;br&gt;méng&lt;br&gt;柠檬 (檸檬) níngméng lemon</A>
</item>
<item id='_13'>
<cat>Most common Chinese characters 2810-2831 - English</cat>
<Q>Write the character:&lt;br&gt;crouch</Q>
<A>蹲 (strokes unavailable)&lt;br&gt;cún&lt;br&gt;蹲点 (蹲點) cúndiǎn of caders stay at a selected grass-roots unit to</A>
</item>
<item id='_14'>
<cat>Most common Chinese characters 2810-2831 - English</cat>
<Q>Write the character:&lt;br&gt;addicted to; fond of; stem corresponding to -phil or -phile</Q>
<A>嗜 (strokes unavailable)&lt;br&gt;shì&lt;br&gt;嗜好 shìhào fondness; hobby; indulgence</A>
</item>
<item id='_15'>
<cat>Most common Chinese characters 2810-2831 - English</cat>
<Q>Write the character:&lt;br&gt;waterfall</Q>
<A>瀑 (strokes unavailable)&lt;br&gt;pù&lt;br&gt;瀑布 pùbù waterfall</A>
</item>
<item id='_16'>
<cat>Most common Chinese characters 2810-2831 - English</cat>
<Q>Write the character:&lt;br&gt;rare</Q>
<A>罕 (strokes unavailable)&lt;br&gt;hǎn&lt;br&gt;罕见 (罕見) hǎnjiàn rare; rarely seen</A>
</item>
<item id='_17'>
<cat>Most common Chinese characters 2810-2831 - English</cat>
<Q>Write the character:&lt;br&gt;laborious; small stone; to record; to tape; to write down; to hire; to employ</Q>
<A>碌 (strokes unavailable)&lt;br&gt;lù&lt;br&gt;忙碌 mánglù busy; bustling</A>
</item>
<item id='_18'>
<cat>Most common Chinese characters 2810-2831 - English</cat>
<Q>Write the character:&lt;br&gt;deceive; scare; to travel</Q>
<A>迋 (strokes unavailable)&lt;br&gt;wàng</A>
</item>
<item id='_19'>
<cat>Most common Chinese characters 2810-2831 - English</cat>
<Q>Write the character:&lt;br&gt;paddy; rice</Q>
<A>稻 (strokes unavailable)&lt;br&gt;dào&lt;br&gt;水稻 shuǐdào rice; paddy</A>
</item>
<item id='_20'>
<cat>Most common Chinese characters 2810-2831 - Hanzi</cat>
<Q>袂</Q>
<A>mèi&lt;br&gt;sleeve of a robe</A>
</item>
<item id='_21'>
<cat>Most common Chinese characters 2810-2831 - Hanzi</cat>
<Q>僵</Q>
<A>jiāng&lt;br&gt;rigid&lt;br&gt;僵硬 jiāngyìng stark; stiff</A>
</item>
<item id='_22'>
<cat>Most common Chinese characters 2810-2831 - Hanzi</cat>
<Q>尴</Q>
<A>traditional: 尷&lt;br&gt;gān&lt;br&gt;embarrassed; ill at ease</A>
</item>
<item id='_23'>
<cat>Most common Chinese characters 2810-2831 - Hanzi</cat>
<Q>缔</Q>
<A>traditional: 締&lt;br&gt;dì&lt;br&gt;closely joined; connection; knot&lt;br&gt;缔结 (締結) dìjié (v) conclude (an agreement)</A>
</item>
<item id='_24'>
<cat>Most common Chinese characters 2810-2831 - Hanzi</cat>
<Q>槟</Q>
<A>traditional: 檳&lt;br&gt;1: bīn 2: bīng&lt;br&gt;1: areca; the areca nut palm&lt;br&gt;2: areca&lt;br&gt;槟榔 (檳榔) bīnláng areca 槟榔 (檳榔) bīnglang betel palm (Areca catechu); betel nut</A>
</item>
<item id='_25'>
<cat>Most common Chinese characters 2810-2831 - Hanzi</cat>
<Q>扎</Q>
<A>traditional: 紮&lt;br&gt;zā&lt;br&gt;tie with string or ribbon; bind with rope or cord; to stop&lt;br&gt;包扎 (包紮) bāozā to bind; to wrap up; to bind up; to pack</A>
</item>
<item id='_26'>
<cat>Most common Chinese characters 2810-2831 - Hanzi</cat>
<Q>斧</Q>
<A>fǔ&lt;br&gt;hatchet&lt;br&gt;斧头 (斧頭) fǔtóu ax; hatchet</A>
</item>
<item id='_27'>
<cat>Most common Chinese characters 2810-2831 - Hanzi</cat>
<Q>襟</Q>
<A>jīn&lt;br&gt;lapel; overlap of Chinese gown; fig. bosom (the seat of emotions); to cherish (ambition, desires, honorable intentions etc) in one's bosom&lt;br&gt;胸襟 xiōngjīn lapel of jacket; heart; aspiration; vision</A>
</item>
<item id='_28'>
<cat>Most common Chinese characters 2810-2831 - Hanzi</cat>
<Q>辖</Q>
<A>traditional: 轄&lt;br&gt;xía&lt;br&gt;have jurisdiction over; linchpin of a wheel (archaic)&lt;br&gt;管辖 (管轄) guǎnxía administer; have jurisdiction (over)</A>
</item>
<item id='_29'>
<cat>Most common Chinese characters 2810-2831 - Hanzi</cat>
<Q>肖</Q>
<A>xiào&lt;br&gt;similar; resembling; to resemble; to be like&lt;br&gt;肖像 xiàoxiàng portrait</A>
</item>
<item id='_30'>
<cat>Most common Chinese characters 2810-2831 - Hanzi</cat>
<Q>钝</Q>
<A>traditional: 鈍&lt;br&gt;dùn&lt;br&gt;blunt; stupid&lt;br&gt;钝角 (鈍角) dùnjǐa obtuse angle</A>
</item>
<item id='_31'>
<cat>Most common Chinese characters 2810-2831 - Hanzi</cat>
<Q>肿</Q>
<A>traditional: 腫&lt;br&gt;zhǒng&lt;br&gt;swollen&lt;br&gt;水肿 (水腫) shuǐzhǒng (med.) edema; dropsy</A>
</item>
<item id='_32'>
<cat>Most common Chinese characters 2810-2831 - Hanzi</cat>
<Q>檬</Q>
<A>méng&lt;br&gt;lemon&lt;br&gt;柠檬 (檸檬) níngméng lemon</A>
</item>
<item id='_33'>
<cat>Most common Chinese characters 2810-2831 - Hanzi</cat>
<Q>蹲</Q>
<A>cún&lt;br&gt;crouch&lt;br&gt;蹲点 (蹲點) cúndiǎn of caders stay at a selected grass-roots unit to</A>
</item>
<item id='_34'>
<cat>Most common Chinese characters 2810-2831 - Hanzi</cat>
<Q>嗜</Q>
<A>shì&lt;br&gt;addicted to; fond of; stem corresponding to -phil or -phile&lt;br&gt;嗜好 shìhào fondness; hobby; indulgence</A>
</item>
<item id='_35'>
<cat>Most common Chinese characters 2810-2831 - Hanzi</cat>
<Q>瀑</Q>
<A>pù&lt;br&gt;waterfall&lt;br&gt;瀑布 pùbù waterfall</A>
</item>
<item id='_36'>
<cat>Most common Chinese characters 2810-2831 - Hanzi</cat>
<Q>罕</Q>
<A>hǎn&lt;br&gt;rare&lt;br&gt;罕见 (罕見) hǎnjiàn rare; rarely seen</A>
</item>
<item id='_37'>
<cat>Most common Chinese characters 2810-2831 - Hanzi</cat>
<Q>碌</Q>
<A>lù&lt;br&gt;laborious; small stone; to record; to tape; to write down; to hire; to employ&lt;br&gt;忙碌 mánglù busy; bustling</A>
</item>
<item id='_38'>
<cat>Most common Chinese characters 2810-2831 - Hanzi</cat>
<Q>迋</Q>
<A>wàng&lt;br&gt;deceive; scare; to travel</A>
</item>
<item id='_39'>
<cat>Most common Chinese characters 2810-2831 - Hanzi</cat>
<Q>稻</Q>
<A>dào&lt;br&gt;paddy; rice&lt;br&gt;水稻 shuǐdào rice; paddy</A>
</item>
<item id='_40'>
<cat>Most common Chinese characters 2810-2831 - Traditional</cat>
<Q>尷</Q>
<A>simplified: 尴&lt;br&gt;gān&lt;br&gt;embarrassed; ill at ease</A>
</item>
<item id='_41'>
<cat>Most common Chinese characters 2810-2831 - Traditional</cat>
<Q>締</Q>
<A>simplified: 缔&lt;br&gt;dì&lt;br&gt;closely joined; connection; knot&lt;br&gt;缔结 (締結) dìjié (v) conclude (an agreement)</A>
</item>
<item id='_42'>
<cat>Most common Chinese characters 2810-2831 - Traditional</cat>
<Q>檳</Q>
<A>simplified: 槟&lt;br&gt;1: bīn 2: bīng&lt;br&gt;1: areca; the areca nut palm&lt;br&gt;2: areca&lt;br&gt;槟榔 (檳榔) bīnláng areca 槟榔 (檳榔) bīnglang betel palm (Areca catechu); betel nut</A>
</item>
<item id='_43'>
<cat>Most common Chinese characters 2810-2831 - Traditional</cat>
<Q>紮</Q>
<A>simplified: 扎&lt;br&gt;zā&lt;br&gt;tie with string or ribbon; bind with rope or cord; to stop&lt;br&gt;包扎 (包紮) bāozā to bind; to wrap up; to bind up; to pack</A>
</item>
<item id='_44'>
<cat>Most common Chinese characters 2810-2831 - Traditional</cat>
<Q>轄</Q>
<A>simplified: 辖&lt;br&gt;xía&lt;br&gt;have jurisdiction over; linchpin of a wheel (archaic)&lt;br&gt;管辖 (管轄) guǎnxía administer; have jurisdiction (over)</A>
</item>
<item id='_45'>
<cat>Most common Chinese characters 2810-2831 - Traditional</cat>
<Q>鈍</Q>
<A>simplified: 钝&lt;br&gt;dùn&lt;br&gt;blunt; stupid&lt;br&gt;钝角 (鈍角) dùnjǐa obtuse angle</A>
</item>
<item id='_46'>
<cat>Most common Chinese characters 2810-2831 - Traditional</cat>
<Q>腫</Q>
<A>simplified: 肿&lt;br&gt;zhǒng&lt;br&gt;swollen&lt;br&gt;水肿 (水腫) shuǐzhǒng (med.) edema; dropsy</A>
</item>
<item id='_47'>
<cat>Most common Chinese characters 2810-2831 - Pinyin</cat>
<Q>Write the character: mèi</Q>
<A>袂 (strokes unavailable)&lt;br&gt;sleeve of a robe</A>
</item>
<item id='_48'>
<cat>Most common Chinese characters 2810-2831 - Pinyin</cat>
<Q>Write the character: jiāng&lt;br&gt;(jiāngyìng de jiāng)</Q>
<A>僵 (strokes unavailable)&lt;br&gt;rigid&lt;br&gt;僵硬 jiāngyìng stark; stiff</A>
</item>
<item id='_49'>
<cat>Most common Chinese characters 2810-2831 - Pinyin</cat>
<Q>Write the character: gān</Q>
<A>尴 (strokes unavailable)&lt;br&gt;traditional: 尷&lt;br&gt;embarrassed; ill at ease</A>
</item>
<item id='_50'>
<cat>Most common Chinese characters 2810-2831 - Pinyin</cat>
<Q>Write the character: dì&lt;br&gt;(dìjié de dì)</Q>
<A>缔 (strokes unavailable)&lt;br&gt;traditional: 締&lt;br&gt;closely joined; connection; knot&lt;br&gt;缔结 (締結) dìjié (v) conclude (an agreement)</A>
</item>
<item id='_51'>
<cat>Most common Chinese characters 2810-2831 - Pinyin</cat>
<Q>Write the character: bīn&lt;br&gt;(bīnláng de bīn)</Q>
<A>槟 (strokes unavailable)&lt;br&gt;traditional: 檳&lt;br&gt;areca; the areca nut palm&lt;br&gt;槟榔 (檳榔) bīnláng areca</A>
</item>
<item id='_52'>
<cat>Most common Chinese characters 2810-2831 - Pinyin</cat>
<Q>Write the character: bīng&lt;br&gt;(bīnglang de bīng)</Q>
<A>槟 (strokes unavailable)&lt;br&gt;traditional: 檳&lt;br&gt;areca&lt;br&gt;槟榔 (檳榔) bīnglang betel palm (Areca catechu); betel nut</A>
</item>
<item id='_53'>
<cat>Most common Chinese characters 2810-2831 - Pinyin</cat>
<Q>Write the character: zā&lt;br&gt;(bāozā de zā)</Q>
<A>扎 (strokes unavailable)&lt;br&gt;traditional: 紮&lt;br&gt;tie with string or ribbon; bind with rope or cord; to stop&lt;br&gt;包扎 (包紮) bāozā to bind; to wrap up; to bind up; to pack</A>
</item>
<item id='_54'>
<cat>Most common Chinese characters 2810-2831 - Pinyin</cat>
<Q>Write the character: fǔ&lt;br&gt;(fǔtóu de fǔ)</Q>
<A>斧 (strokes unavailable)&lt;br&gt;hatchet&lt;br&gt;斧头 (斧頭) fǔtóu ax; hatchet</A>
</item>
<item id='_55'>
<cat>Most common Chinese characters 2810-2831 - Pinyin</cat>
<Q>Write the character: jīn&lt;br&gt;(xiōngjīn de jīn)</Q>
<A>襟 (strokes unavailable)&lt;br&gt;lapel; overlap of Chinese gown; fig. bosom (the seat of emotions); to cherish (ambition, desires, honorable intentions etc) in one's bosom&lt;br&gt;胸襟 xiōngjīn lapel of jacket; heart; aspiration; vision</A>
</item>
<item id='_56'>
<cat>Most common Chinese characters 2810-2831 - Pinyin</cat>
<Q>Write the character: xía&lt;br&gt;(guǎnxía de xía)</Q>
<A>辖 (strokes unavailable)&lt;br&gt;traditional: 轄&lt;br&gt;have jurisdiction over; linchpin of a wheel (archaic)&lt;br&gt;管辖 (管轄) guǎnxía administer; have jurisdiction (over)</A>
</item>
<item id='_57'>
<cat>Most common Chinese characters 2810-2831 - Pinyin</cat>
<Q>Write the character: xiào&lt;br&gt;(xiàoxiàng de xiào)</Q>
<A>肖 (strokes unavailable)&lt;br&gt;similar; resembling; to resemble; to be like&lt;br&gt;肖像 xiàoxiàng portrait</A>
</item>
<item id='_58'>
<cat>Most common Chinese characters 2810-2831 - Pinyin</cat>
<Q>Write the character: dùn&lt;br&gt;(dùnjǐa de dùn)</Q>
<A>钝 (strokes unavailable)&lt;br&gt;traditional: 鈍&lt;br&gt;blunt; stupid&lt;br&gt;钝角 (鈍角) dùnjǐa obtuse angle</A>
</item>
<item id='_59'>
<cat>Most common Chinese characters 2810-2831 - Pinyin</cat>
<Q>Write the character: zhǒng&lt;br&gt;(shuǐzhǒng de zhǒng)</Q>
<A>肿 (strokes unavailable)&lt;br&gt;traditional: 腫&lt;br&gt;swollen&lt;br&gt;水肿 (水腫) shuǐzhǒng (med.) edema; dropsy</A>
</item>
<item id='_60'>
<cat>Most common Chinese characters 2810-2831 - Pinyin</cat>
<Q>Write the character: méng&lt;br&gt;(níngméng de méng)</Q>
<A>檬 (strokes unavailable)&lt;br&gt;lemon&lt;br&gt;柠檬 (檸檬) níngméng lemon</A>
</item>
<item id='_61'>
<cat>Most common Chinese characters 2810-2831 - Pinyin</cat>
<Q>Write the character: cún&lt;br&gt;(cúndiǎn de cún)</Q>
<A>蹲 (strokes unavailable)&lt;br&gt;crouch&lt;br&gt;蹲点 (蹲點) cúndiǎn of caders stay at a selected grass-roots unit to</A>
</item>
<item id='_62'>
<cat>Most common Chinese characters 2810-2831 - Pinyin</cat>
<Q>Write the character: shì&lt;br&gt;(shìhào de shì)</Q>
<A>嗜 (strokes unavailable)&lt;br&gt;addicted to; fond of; stem corresponding to -phil or -phile&lt;br&gt;嗜好 shìhào fondness; hobby; indulgence</A>
</item>
<item id='_63'>
<cat>Most common Chinese characters 2810-2831 - Pinyin</cat>
<Q>Write the character: pù&lt;br&gt;(pùbù de pù)</Q>
<A>瀑 (strokes unavailable)&lt;br&gt;waterfall&lt;br&gt;瀑布 pùbù waterfall</A>
</item>
<item id='_64'>
<cat>Most common Chinese characters 2810-2831 - Pinyin</cat>
<Q>Write the character: hǎn&lt;br&gt;(hǎnjiàn de hǎn)</Q>
<A>罕 (strokes unavailable)&lt;br&gt;rare&lt;br&gt;罕见 (罕見) hǎnjiàn rare; rarely seen</A>
</item>
<item id='_65'>
<cat>Most common Chinese characters 2810-2831 - Pinyin</cat>
<Q>Write the character: lù&lt;br&gt;(mánglù de lù)</Q>
<A>碌 (strokes unavailable)&lt;br&gt;laborious; small stone; to record; to tape; to write down; to hire; to employ&lt;br&gt;忙碌 mánglù busy; bustling</A>
</item>
<item id='_66'>
<cat>Most common Chinese characters 2810-2831 - Pinyin</cat>
<Q>Write the character: wàng</Q>
<A>迋 (strokes unavailable)&lt;br&gt;deceive; scare; to travel</A>
</item>
<item id='_67'>
<cat>Most common Chinese characters 2810-2831 - Pinyin</cat>
<Q>Write the character: dào&lt;br&gt;(shuǐdào de dào)</Q>
<A>稻 (strokes unavailable)&lt;br&gt;paddy; rice&lt;br&gt;水稻 shuǐdào rice; paddy</A>
</item>
<item id='_68'>
<cat>Most common Chinese characters 2810-2831 - Words</cat>
<Q>僵化</Q>
<A>jiānghuà become rigid</A>
</item>
<item id='_69'>
<cat>Most common Chinese characters 2810-2831 - Words</cat>
<Q>僵局</Q>
<A>jiāngjú impasse; deadlock</A>
</item>
<item id='_70'>
<cat>Most common Chinese characters 2810-2831 - Words</cat>
<Q>僵硬</Q>
<A>jiāngyìng stark; stiff</A>
</item>
<item id='_71'>
<cat>Most common Chinese characters 2810-2831 - Words</cat>
<Q>冻僵</Q>
<A>traditional: 凍僵&lt;br&gt;dòngjiāng frozen stiff</A>
</item>
<item id='_72'>
<cat>Most common Chinese characters 2810-2831 - Words</cat>
<Q>取缔</Q>
<A>traditional: 取締&lt;br&gt;qǔdì ban; outlaw; prohibit; suppress</A>
</item>
<item id='_73'>
<cat>Most common Chinese characters 2810-2831 - Words</cat>
<Q>结缔组织</Q>
<A>traditional: 結締組織&lt;br&gt;jiédìzǔzhī connective tissue</A>
</item>
<item id='_74'>
<cat>Most common Chinese characters 2810-2831 - Words</cat>
<Q>缔结</Q>
<A>traditional: 締結&lt;br&gt;dìjié (v) conclude (an agreement)</A>
</item>
<item id='_75'>
<cat>Most common Chinese characters 2810-2831 - Words</cat>
<Q>缔造</Q>
<A>traditional: 締造&lt;br&gt;dìzào to found; to create</A>
</item>
<item id='_76'>
<cat>Most common Chinese characters 2810-2831 - Words</cat>
<Q>包扎</Q>
<A>traditional: 包紮&lt;br&gt;bāozā to bind; to wrap up; to bind up; to pack</A>
</item>
<item id='_77'>
<cat>Most common Chinese characters 2810-2831 - Words</cat>
<Q>驻扎</Q>
<A>traditional: 駐紮&lt;br&gt;zhùzhā to station; to garrison (troops)</A>
</item>
<item id='_78'>
<cat>Most common Chinese characters 2810-2831 - Words</cat>
<Q>大刀阔斧</Q>
<A>traditional: 大刀闊斧&lt;br&gt;dàdāokuòfǔ bold and decisive</A>
</item>
<item id='_79'>
<cat>Most common Chinese characters 2810-2831 - Words</cat>
<Q>斧子</Q>
<A>fǔzi axe; hatchet</A>
</item>
<item id='_80'>
<cat>Most common Chinese characters 2810-2831 - Words</cat>
<Q>斧头</Q>
<A>traditional: 斧頭&lt;br&gt;fǔtóu ax; hatchet</A>
</item>
<item id='_81'>
<cat>Most common Chinese characters 2810-2831 - Words</cat>
<Q>胸襟</Q>
<A>xiōngjīn lapel of jacket; heart; aspiration; vision</A>
</item>
<item id='_82'>
<cat>Most common Chinese characters 2810-2831 - Words</cat>
<Q>直辖市</Q>
<A>traditional: 直轄市&lt;br&gt;zhíxíashì municipality, namely Beijing 北京, Tianjin 天津, Shanghai 上海 and Chongqing 重慶|重庆, the first level administrative subdivision; province-level city; also called directly governed city</A>
</item>
<item id='_83'>
<cat>Most common Chinese characters 2810-2831 - Words</cat>
<Q>管辖</Q>
<A>traditional: 管轄&lt;br&gt;guǎnxía administer; have jurisdiction (over)</A>
</item>
<item id='_84'>
<cat>Most common Chinese characters 2810-2831 - Words</cat>
<Q>统辖</Q>
<A>traditional: 統轄&lt;br&gt;tǒngxía to govern; to have complete control over; to be in command of</A>
</item>
<item id='_85'>
<cat>Most common Chinese characters 2810-2831 - Words</cat>
<Q>辖区</Q>
<A>traditional: 轄區&lt;br&gt;xíaqū administrative region</A>
</item>
<item id='_86'>
<cat>Most common Chinese characters 2810-2831 - Words</cat>
<Q>不肖</Q>
<A>bùxiào unworthy</A>
</item>
<item id='_87'>
<cat>Most common Chinese characters 2810-2831 - Words</cat>
<Q>努瓦克肖特</Q>
<A>nǔwǎkèxiàotè Nouakchott (capital of Mauritania)</A>
</item>
<item id='_88'>
<cat>Most common Chinese characters 2810-2831 - Words</cat>
<Q>肖像</Q>
<A>xiàoxiàng portrait</A>
</item>
<item id='_89'>
<cat>Most common Chinese characters 2810-2831 - Words</cat>
<Q>迟钝</Q>
<A>traditional: 遲鈍&lt;br&gt;chídùn slow (witted); stupid</A>
</item>
<item id='_90'>
<cat>Most common Chinese characters 2810-2831 - Words</cat>
<Q>钝角</Q>
<A>traditional: 鈍角&lt;br&gt;dùnjǐa obtuse angle</A>
</item>
<item id='_91'>
<cat>Most common Chinese characters 2810-2831 - Words</cat>
<Q>水肿</Q>
<A>traditional: 水腫&lt;br&gt;shuǐzhǒng (med.) edema; dropsy</A>
</item>
<item id='_92'>
<cat>Most common Chinese characters 2810-2831 - Words</cat>
<Q>浮肿</Q>
<A>traditional: 浮腫&lt;br&gt;fúzhǒng edema (accumulation of interstitial fluids in internal organs); dropsy</A>
</item>
<item id='_93'>
<cat>Most common Chinese characters 2810-2831 - Words</cat>
<Q>红肿</Q>
<A>traditional: 紅腫&lt;br&gt;hóngzhǒng inflamed; red and swollen</A>
</item>
<item id='_94'>
<cat>Most common Chinese characters 2810-2831 - Words</cat>
<Q>肿胀</Q>
<A>traditional: 腫脹&lt;br&gt;zhǒngzhàng swelling</A>
</item>
<item id='_95'>
<cat>Most common Chinese characters 2810-2831 - Words</cat>
<Q>蹲点</Q>
<A>traditional: 蹲點&lt;br&gt;cúndiǎn of caders stay at a selected grass-roots unit to</A>
</item>
<item id='_96'>
<cat>Most common Chinese characters 2810-2831 - Words</cat>
<Q>嗜好</Q>
<A>shìhào fondness; hobby; indulgence</A>
</item>
<item id='_97'>
<cat>Most common Chinese characters 2810-2831 - Words</cat>
<Q>瀑布</Q>
<A>pùbù waterfall</A>
</item>
<item id='_98'>
<cat>Most common Chinese characters 2810-2831 - Words</cat>
<Q>希罕</Q>
<A>xīhǎn rare</A>
</item>
<item id='_99'>
<cat>Most common Chinese characters 2810-2831 - Words</cat>
<Q>稀罕</Q>
<A>xīhan rare; scarce; uncommon; to value as a rarity; to cherish&lt;br&gt;xīhǎn rareness</A>
</item>
<item id='_100'>
<cat>Most common Chinese characters 2810-2831 - Words</cat>
<Q>罕见</Q>
<A>traditional: 罕見&lt;br&gt;hǎnjiàn rare; rarely seen</A>
</item>
<item id='_101'>
<cat>Most common Chinese characters 2810-2831 - Words</cat>
<Q>忙碌</Q>
<A>mángliù busy&lt;br&gt;mánglù busy; bustling</A>
</item>
<item id='_102'>
<cat>Most common Chinese characters 2810-2831 - Words</cat>
<Q>水稻</Q>
<A>shuǐdào rice; paddy</A>
</item>
<item id='_103'>
<cat>Most common Chinese characters 2810-2831 - Words</cat>
<Q>稻子</Q>
<A>dàozi (n) unhulled rice</A>
</item>
<item id='_104'>
<cat>Most common Chinese characters 2810-2831 - Words</cat>
<Q>稻田</Q>
<A>dàotián cornfield</A>
</item>
<item id='_105'>
<cat>Most common Chinese characters 2810-2831 - Words</cat>
<Q>稻米</Q>
<A>dàomǐ rice (crop)</A>
</item>
<item id='_106'>
<cat>Most common Chinese characters 2810-2831 - Words</cat>
<Q>稻草</Q>
<A>dàocǎo straw</A>
</item>
</mnemosyne>
