<?xml version='1.0' encoding='UTF-8'?>
<mnemosyne core_version='1'>
<category active='1'>
<name>Most common Chinese characters 2092-2104 - English</name>
</category>
<category active='1'>
<name>Most common Chinese characters 2092-2104 - Hanzi</name>
</category>
<category active='1'>
<name>Most common Chinese characters 2092-2104 - Traditional</name>
</category>
<category active='1'>
<name>Most common Chinese characters 2092-2104 - Pinyin</name>
</category>
<category active='1'>
<name>Most common Chinese characters 2092-2104 - Words</name>
</category>
<item id='_0'>
<cat>Most common Chinese characters 2092-2104 - English</cat>
<Q>Write the character:&lt;br&gt;the Jin dynasties (265-420 AD); the Western Jin 西晉|西晋 (265-316), Eastern Jin 東晉|东晋 (317-420) and Later Jin dynasty (936-946); abbr. for Shanxi province 山西</Q>
<A>&lt;img src="stroke-images/2092.png"&gt;&lt;br&gt;traditional: 晉&lt;br&gt;Jìn&lt;br&gt;晋书 (晉書) Jìnshū History of the Jin dynasty, fifth of the 24 dynastic histories 二十四史, compiled under Fang Xuanling 房玄齡 in 648 during Tang dynasty 唐朝, 130 scrolls</A>
</item>
<item id='_1'>
<cat>Most common Chinese characters 2092-2104 - English</cat>
<Q>Write the character:&lt;br&gt;diluted; sparse</Q>
<A>稀 (strokes unavailable)&lt;br&gt;xī&lt;br&gt;稀释 (稀釋) xīshì to disperse</A>
</item>
<item id='_2'>
<cat>Most common Chinese characters 2092-2104 - English</cat>
<Q>Write the character:&lt;br&gt;duck</Q>
<A>鸭 (strokes unavailable)&lt;br&gt;traditional: 鴨&lt;br&gt;yā&lt;br&gt;鸭子 (鴨子) yāzi duck</A>
</item>
<item id='_3'>
<cat>Most common Chinese characters 2092-2104 - English</cat>
<Q>Write the character:&lt;br&gt;1: perspiration; sweat; Khan (Persian or Mongol king or emperor); Khan (name)&lt;br&gt;2: sweat</Q>
<A>&lt;img src="stroke-images/2095.png"&gt;&lt;br&gt;1: hàn 2: hán&lt;br&gt;阿富汗 A1fùhàn Afghanistan; Afghan 阿富汗 āfùhán Afghanistan</A>
</item>
<item id='_4'>
<cat>Most common Chinese characters 2092-2104 - English</cat>
<Q>Write the character:&lt;br&gt;male</Q>
<A>牡 (strokes unavailable)&lt;br&gt;mǔ&lt;br&gt;牡丹 mǔdān peony (type of flower)</A>
</item>
<item id='_5'>
<cat>Most common Chinese characters 2092-2104 - English</cat>
<Q>Write the character:&lt;br&gt;smooth; fluent; joyful; happy</Q>
<A>畅 (strokes unavailable)&lt;br&gt;traditional: 暢&lt;br&gt;chàng&lt;br&gt;畅通 (暢通) chàngtōng (adj) unclogged; unimpeded; free-flowing; (v)move without being impeded</A>
</item>
<item id='_6'>
<cat>Most common Chinese characters 2092-2104 - English</cat>
<Q>Write the character:&lt;br&gt;to add; to increase; to replenish</Q>
<A>添 (strokes unavailable)&lt;br&gt;tiān&lt;br&gt;增添 zēngtiān add to; increase</A>
</item>
<item id='_7'>
<cat>Most common Chinese characters 2092-2104 - English</cat>
<Q>Write the character:&lt;br&gt;goblin; witch; devil; bewitching; enchanting; monster; phantom</Q>
<A>妖 (strokes unavailable)&lt;br&gt;yāo&lt;br&gt;妖魔 yāomó demon</A>
</item>
<item id='_8'>
<cat>Most common Chinese characters 2092-2104 - English</cat>
<Q>Write the character:&lt;br&gt;dose</Q>
<A>剂 (strokes unavailable)&lt;br&gt;traditional: 劑&lt;br&gt;jì&lt;br&gt;溶剂 (溶劑) róngjì solvent</A>
</item>
<item id='_9'>
<cat>Most common Chinese characters 2092-2104 - English</cat>
<Q>Write the character:&lt;br&gt;to overflow</Q>
<A>泛 (strokes unavailable)&lt;br&gt;fán&lt;br&gt;泛非主义 (泛非主義) fánfēizhǔyì Pan-Africanism</A>
</item>
<item id='_10'>
<cat>Most common Chinese characters 2092-2104 - English</cat>
<Q>Write the character:&lt;br&gt;firewood; surname Chai</Q>
<A>柴 (strokes unavailable)&lt;br&gt;chái&lt;br&gt;柴油机 (柴油機) cháiyóujī diesel engine</A>
</item>
<item id='_11'>
<cat>Most common Chinese characters 2092-2104 - English</cat>
<Q>Write the character:&lt;br&gt;to carry; to take along; to bring along; to hold (hands)</Q>
<A>携 (strokes unavailable)&lt;br&gt;traditional: 攜&lt;br&gt;xié&lt;br&gt;携带 (攜帶) xiédài to carry; portable</A>
</item>
<item id='_12'>
<cat>Most common Chinese characters 2092-2104 - Hanzi</cat>
<Q>晋</Q>
<A>traditional: 晉&lt;br&gt;Jìn&lt;br&gt;the Jin dynasties (265-420 AD); the Western Jin 西晉|西晋 (265-316), Eastern Jin 東晉|东晋 (317-420) and Later Jin dynasty (936-946); abbr. for Shanxi province 山西&lt;br&gt;晋书 (晉書) Jìnshū History of the Jin dynasty, fifth of the 24 dynastic histories 二十四史, compiled under Fang Xuanling 房玄齡 in 648 during Tang dynasty 唐朝, 130 scrolls</A>
</item>
<item id='_13'>
<cat>Most common Chinese characters 2092-2104 - Hanzi</cat>
<Q>稀</Q>
<A>xī&lt;br&gt;diluted; sparse&lt;br&gt;稀释 (稀釋) xīshì to disperse</A>
</item>
<item id='_14'>
<cat>Most common Chinese characters 2092-2104 - Hanzi</cat>
<Q>鸭</Q>
<A>traditional: 鴨&lt;br&gt;yā&lt;br&gt;duck&lt;br&gt;鸭子 (鴨子) yāzi duck</A>
</item>
<item id='_15'>
<cat>Most common Chinese characters 2092-2104 - Hanzi</cat>
<Q>汗</Q>
<A>1: hàn 2: hán&lt;br&gt;1: perspiration; sweat; Khan (Persian or Mongol king or emperor); Khan (name)&lt;br&gt;2: sweat&lt;br&gt;阿富汗 A1fùhàn Afghanistan; Afghan 阿富汗 āfùhán Afghanistan</A>
</item>
<item id='_16'>
<cat>Most common Chinese characters 2092-2104 - Hanzi</cat>
<Q>牡</Q>
<A>mǔ&lt;br&gt;male&lt;br&gt;牡丹 mǔdān peony (type of flower)</A>
</item>
<item id='_17'>
<cat>Most common Chinese characters 2092-2104 - Hanzi</cat>
<Q>畅</Q>
<A>traditional: 暢&lt;br&gt;chàng&lt;br&gt;smooth; fluent; joyful; happy&lt;br&gt;畅通 (暢通) chàngtōng (adj) unclogged; unimpeded; free-flowing; (v)move without being impeded</A>
</item>
<item id='_18'>
<cat>Most common Chinese characters 2092-2104 - Hanzi</cat>
<Q>添</Q>
<A>tiān&lt;br&gt;to add; to increase; to replenish&lt;br&gt;增添 zēngtiān add to; increase</A>
</item>
<item id='_19'>
<cat>Most common Chinese characters 2092-2104 - Hanzi</cat>
<Q>妖</Q>
<A>yāo&lt;br&gt;goblin; witch; devil; bewitching; enchanting; monster; phantom&lt;br&gt;妖魔 yāomó demon</A>
</item>
<item id='_20'>
<cat>Most common Chinese characters 2092-2104 - Hanzi</cat>
<Q>剂</Q>
<A>traditional: 劑&lt;br&gt;jì&lt;br&gt;dose&lt;br&gt;溶剂 (溶劑) róngjì solvent</A>
</item>
<item id='_21'>
<cat>Most common Chinese characters 2092-2104 - Hanzi</cat>
<Q>泛</Q>
<A>fán&lt;br&gt;to overflow&lt;br&gt;泛非主义 (泛非主義) fánfēizhǔyì Pan-Africanism</A>
</item>
<item id='_22'>
<cat>Most common Chinese characters 2092-2104 - Hanzi</cat>
<Q>柴</Q>
<A>chái&lt;br&gt;firewood; surname Chai&lt;br&gt;柴油机 (柴油機) cháiyóujī diesel engine</A>
</item>
<item id='_23'>
<cat>Most common Chinese characters 2092-2104 - Hanzi</cat>
<Q>携</Q>
<A>traditional: 攜&lt;br&gt;xié&lt;br&gt;to carry; to take along; to bring along; to hold (hands)&lt;br&gt;携带 (攜帶) xiédài to carry; portable</A>
</item>
<item id='_24'>
<cat>Most common Chinese characters 2092-2104 - Traditional</cat>
<Q>晉</Q>
<A>simplified: 晋&lt;br&gt;Jìn&lt;br&gt;the Jin dynasties (265-420 AD); the Western Jin 西晉|西晋 (265-316), Eastern Jin 東晉|东晋 (317-420) and Later Jin dynasty (936-946); abbr. for Shanxi province 山西&lt;br&gt;晋书 (晉書) Jìnshū History of the Jin dynasty, fifth of the 24 dynastic histories 二十四史, compiled under Fang Xuanling 房玄齡 in 648 during Tang dynasty 唐朝, 130 scrolls</A>
</item>
<item id='_25'>
<cat>Most common Chinese characters 2092-2104 - Traditional</cat>
<Q>鴨</Q>
<A>simplified: 鸭&lt;br&gt;yā&lt;br&gt;duck&lt;br&gt;鸭子 (鴨子) yāzi duck</A>
</item>
<item id='_26'>
<cat>Most common Chinese characters 2092-2104 - Traditional</cat>
<Q>暢</Q>
<A>simplified: 畅&lt;br&gt;chàng&lt;br&gt;smooth; fluent; joyful; happy&lt;br&gt;畅通 (暢通) chàngtōng (adj) unclogged; unimpeded; free-flowing; (v)move without being impeded</A>
</item>
<item id='_27'>
<cat>Most common Chinese characters 2092-2104 - Traditional</cat>
<Q>劑</Q>
<A>simplified: 剂&lt;br&gt;jì&lt;br&gt;dose&lt;br&gt;溶剂 (溶劑) róngjì solvent</A>
</item>
<item id='_28'>
<cat>Most common Chinese characters 2092-2104 - Traditional</cat>
<Q>攜</Q>
<A>simplified: 携&lt;br&gt;xié&lt;br&gt;to carry; to take along; to bring along; to hold (hands)&lt;br&gt;携带 (攜帶) xiédài to carry; portable</A>
</item>
<item id='_29'>
<cat>Most common Chinese characters 2092-2104 - Pinyin</cat>
<Q>Write the character: Jìn&lt;br&gt;(Jìnshū de Jìn)</Q>
<A>&lt;img src="stroke-images/2092.png"&gt;&lt;br&gt;traditional: 晉&lt;br&gt;the Jin dynasties (265-420 AD); the Western Jin 西晉|西晋 (265-316), Eastern Jin 東晉|东晋 (317-420) and Later Jin dynasty (936-946); abbr. for Shanxi province 山西&lt;br&gt;晋书 (晉書) Jìnshū History of the Jin dynasty, fifth of the 24 dynastic histories 二十四史, compiled under Fang Xuanling 房玄齡 in 648 during Tang dynasty 唐朝, 130 scrolls</A>
</item>
<item id='_30'>
<cat>Most common Chinese characters 2092-2104 - Pinyin</cat>
<Q>Write the character: xī&lt;br&gt;(xīshì de xī)</Q>
<A>稀 (strokes unavailable)&lt;br&gt;diluted; sparse&lt;br&gt;稀释 (稀釋) xīshì to disperse</A>
</item>
<item id='_31'>
<cat>Most common Chinese characters 2092-2104 - Pinyin</cat>
<Q>Write the character: yā&lt;br&gt;(yāzi de yā)</Q>
<A>鸭 (strokes unavailable)&lt;br&gt;traditional: 鴨&lt;br&gt;duck&lt;br&gt;鸭子 (鴨子) yāzi duck</A>
</item>
<item id='_32'>
<cat>Most common Chinese characters 2092-2104 - Pinyin</cat>
<Q>Write the character: hàn&lt;br&gt;(A1fùhàn de hàn)</Q>
<A>&lt;img src="stroke-images/2095.png"&gt;&lt;br&gt;perspiration; sweat; Khan (Persian or Mongol king or emperor); Khan (name)&lt;br&gt;阿富汗 A1fùhàn Afghanistan; Afghan</A>
</item>
<item id='_33'>
<cat>Most common Chinese characters 2092-2104 - Pinyin</cat>
<Q>Write the character: hán&lt;br&gt;(āfùhán de hán)</Q>
<A>&lt;img src="stroke-images/2095.png"&gt;&lt;br&gt;sweat&lt;br&gt;阿富汗 āfùhán Afghanistan</A>
</item>
<item id='_34'>
<cat>Most common Chinese characters 2092-2104 - Pinyin</cat>
<Q>Write the character: mǔ&lt;br&gt;(mǔdān de mǔ)</Q>
<A>牡 (strokes unavailable)&lt;br&gt;male&lt;br&gt;牡丹 mǔdān peony (type of flower)</A>
</item>
<item id='_35'>
<cat>Most common Chinese characters 2092-2104 - Pinyin</cat>
<Q>Write the character: chàng&lt;br&gt;(chàngtōng de chàng)</Q>
<A>畅 (strokes unavailable)&lt;br&gt;traditional: 暢&lt;br&gt;smooth; fluent; joyful; happy&lt;br&gt;畅通 (暢通) chàngtōng (adj) unclogged; unimpeded; free-flowing; (v)move without being impeded</A>
</item>
<item id='_36'>
<cat>Most common Chinese characters 2092-2104 - Pinyin</cat>
<Q>Write the character: tiān&lt;br&gt;(zēngtiān de tiān)</Q>
<A>添 (strokes unavailable)&lt;br&gt;to add; to increase; to replenish&lt;br&gt;增添 zēngtiān add to; increase</A>
</item>
<item id='_37'>
<cat>Most common Chinese characters 2092-2104 - Pinyin</cat>
<Q>Write the character: yāo&lt;br&gt;(yāomó de yāo)</Q>
<A>妖 (strokes unavailable)&lt;br&gt;goblin; witch; devil; bewitching; enchanting; monster; phantom&lt;br&gt;妖魔 yāomó demon</A>
</item>
<item id='_38'>
<cat>Most common Chinese characters 2092-2104 - Pinyin</cat>
<Q>Write the character: jì&lt;br&gt;(róngjì de jì)</Q>
<A>剂 (strokes unavailable)&lt;br&gt;traditional: 劑&lt;br&gt;dose&lt;br&gt;溶剂 (溶劑) róngjì solvent</A>
</item>
<item id='_39'>
<cat>Most common Chinese characters 2092-2104 - Pinyin</cat>
<Q>Write the character: fán&lt;br&gt;(fánfēizhǔyì de fán)</Q>
<A>泛 (strokes unavailable)&lt;br&gt;to overflow&lt;br&gt;泛非主义 (泛非主義) fánfēizhǔyì Pan-Africanism</A>
</item>
<item id='_40'>
<cat>Most common Chinese characters 2092-2104 - Pinyin</cat>
<Q>Write the character: chái&lt;br&gt;(cháiyóujī de chái)</Q>
<A>柴 (strokes unavailable)&lt;br&gt;firewood; surname Chai&lt;br&gt;柴油机 (柴油機) cháiyóujī diesel engine</A>
</item>
<item id='_41'>
<cat>Most common Chinese characters 2092-2104 - Pinyin</cat>
<Q>Write the character: xié&lt;br&gt;(xiédài de xié)</Q>
<A>携 (strokes unavailable)&lt;br&gt;traditional: 攜&lt;br&gt;to carry; to take along; to bring along; to hold (hands)&lt;br&gt;携带 (攜帶) xiédài to carry; portable</A>
</item>
<item id='_42'>
<cat>Most common Chinese characters 2092-2104 - Words</cat>
<Q>晋升</Q>
<A>traditional: 晉升&lt;br&gt;jìnshēng to promote to a higher position</A>
</item>
<item id='_43'>
<cat>Most common Chinese characters 2092-2104 - Words</cat>
<Q>晋书</Q>
<A>traditional: 晉書&lt;br&gt;Jìnshū History of the Jin dynasty, fifth of the 24 dynastic histories 二十四史, compiled under Fang Xuanling 房玄齡 in 648 during Tang dynasty 唐朝, 130 scrolls</A>
</item>
<item id='_44'>
<cat>Most common Chinese characters 2092-2104 - Words</cat>
<Q>东晋</Q>
<A>traditional: 東晉&lt;br&gt;Dōngjìn the Eastern Jin dynasty (317-420)&lt;br&gt;dōngjìn the Eastern Jin Dynasty</A>
</item>
<item id='_45'>
<cat>Most common Chinese characters 2092-2104 - Words</cat>
<Q>西晋</Q>
<A>traditional: 西晉&lt;br&gt;Xījìn the Western Jin dynasty (265-316)</A>
</item>
<item id='_46'>
<cat>Most common Chinese characters 2092-2104 - Words</cat>
<Q>稀奇</Q>
<A>xīqí a few scattered</A>
</item>
<item id='_47'>
<cat>Most common Chinese characters 2092-2104 - Words</cat>
<Q>稀少</Q>
<A>xīshǎo rare; rarely</A>
</item>
<item id='_48'>
<cat>Most common Chinese characters 2092-2104 - Words</cat>
<Q>稀有</Q>
<A>xīyǒu uncommon</A>
</item>
<item id='_49'>
<cat>Most common Chinese characters 2092-2104 - Words</cat>
<Q>稀疏</Q>
<A>xīshū sparse; infrequent; thinly spread</A>
</item>
<item id='_50'>
<cat>Most common Chinese characters 2092-2104 - Words</cat>
<Q>稀薄</Q>
<A>xībó rarefaction</A>
</item>
<item id='_51'>
<cat>Most common Chinese characters 2092-2104 - Words</cat>
<Q>稀释</Q>
<A>traditional: 稀釋&lt;br&gt;xīshì to disperse</A>
</item>
<item id='_52'>
<cat>Most common Chinese characters 2092-2104 - Words</cat>
<Q>稀饭</Q>
<A>traditional: 稀飯&lt;br&gt;xīfàn porridge; gruel</A>
</item>
<item id='_53'>
<cat>Most common Chinese characters 2092-2104 - Words</cat>
<Q>北京鸭</Q>
<A>traditional: 北京鴨&lt;br&gt;běijīngyā pekin</A>
</item>
<item id='_54'>
<cat>Most common Chinese characters 2092-2104 - Words</cat>
<Q>野鸭</Q>
<A>traditional: 野鴨&lt;br&gt;yěyā wild duck; mallard (Anas platyrhyncha)</A>
</item>
<item id='_55'>
<cat>Most common Chinese characters 2092-2104 - Words</cat>
<Q>鸭子</Q>
<A>traditional: 鴨子&lt;br&gt;yāzi duck</A>
</item>
<item id='_56'>
<cat>Most common Chinese characters 2092-2104 - Words</cat>
<Q>鸭绿江</Q>
<A>traditional: 鴨綠江&lt;br&gt;Yālùjiāng Yalu River&lt;br&gt;yālùjiāng yalu</A>
</item>
<item id='_57'>
<cat>Most common Chinese characters 2092-2104 - Words</cat>
<Q>冷汗</Q>
<A>lěnghán cold sweat</A>
</item>
<item id='_58'>
<cat>Most common Chinese characters 2092-2104 - Words</cat>
<Q>可汗</Q>
<A>kèhán Khan; Qaghan&lt;br&gt;kěhán cham</A>
</item>
<item id='_59'>
<cat>Most common Chinese characters 2092-2104 - Words</cat>
<Q>成吉思汗</Q>
<A>Chéngjísīhàn Genghis Khan&lt;br&gt;chéngjísīhàn Genghis Khan</A>
</item>
<item id='_60'>
<cat>Most common Chinese characters 2092-2104 - Words</cat>
<Q>血汗</Q>
<A>xuèhàn blood and sweat; sweat and toil</A>
</item>
<item id='_61'>
<cat>Most common Chinese characters 2092-2104 - Words</cat>
<Q>阿富汗</Q>
<A>A1fùhàn Afghanistan; Afghan&lt;br&gt;āfùhàn Afghanistan&lt;br&gt;āfùhán Afghanistan</A>
</item>
<item id='_62'>
<cat>Most common Chinese characters 2092-2104 - Words</cat>
<Q>牡丹</Q>
<A>mǔdān peony (type of flower)</A>
</item>
<item id='_63'>
<cat>Most common Chinese characters 2092-2104 - Words</cat>
<Q>牡丹江</Q>
<A>Mǔdānjiāng (N) Mudanjiang (city in Heilongjiang)&lt;br&gt;mǔdānjiāng Mudanjiang</A>
</item>
<item id='_64'>
<cat>Most common Chinese characters 2092-2104 - Words</cat>
<Q>畅快</Q>
<A>traditional: 暢快&lt;br&gt;chàngkuài carefree</A>
</item>
<item id='_65'>
<cat>Most common Chinese characters 2092-2104 - Words</cat>
<Q>畅所欲言</Q>
<A>traditional: 暢所欲言&lt;br&gt;chàngsuǒyùyán to speak about</A>
</item>
<item id='_66'>
<cat>Most common Chinese characters 2092-2104 - Words</cat>
<Q>畅谈</Q>
<A>traditional: 暢談&lt;br&gt;chàngtán to chat; a long talk; verbose; to talk freely to one's heart's content</A>
</item>
<item id='_67'>
<cat>Most common Chinese characters 2092-2104 - Words</cat>
<Q>畅通</Q>
<A>traditional: 暢通&lt;br&gt;chàngtōng (adj) unclogged; unimpeded; free-flowing; (v)move without being impeded</A>
</item>
<item id='_68'>
<cat>Most common Chinese characters 2092-2104 - Words</cat>
<Q>畅销</Q>
<A>traditional: 暢銷&lt;br&gt;chàngxiāo best seller; chart-topping</A>
</item>
<item id='_69'>
<cat>Most common Chinese characters 2092-2104 - Words</cat>
<Q>流畅</Q>
<A>traditional: 流暢&lt;br&gt;liúchàng flowing (of speech, writing); smooth and easy</A>
</item>
<item id='_70'>
<cat>Most common Chinese characters 2092-2104 - Words</cat>
<Q>舒畅</Q>
<A>traditional: 舒暢&lt;br&gt;shūchàng happy; entirely free from worry</A>
</item>
<item id='_71'>
<cat>Most common Chinese characters 2092-2104 - Words</cat>
<Q>通畅</Q>
<A>traditional: 通暢&lt;br&gt;tōngchàng unobstructed; clear</A>
</item>
<item id='_72'>
<cat>Most common Chinese characters 2092-2104 - Words</cat>
<Q>顺畅</Q>
<A>traditional: 順暢&lt;br&gt;shùnchàng smooth and unhindered; fluent</A>
</item>
<item id='_73'>
<cat>Most common Chinese characters 2092-2104 - Words</cat>
<Q>增添</Q>
<A>zēngtiān add to; increase</A>
</item>
<item id='_74'>
<cat>Most common Chinese characters 2092-2104 - Words</cat>
<Q>添置</Q>
<A>tiānzhì (v) add to one's possesions; acquire; buy</A>
</item>
<item id='_75'>
<cat>Most common Chinese characters 2092-2104 - Words</cat>
<Q>妖道</Q>
<A>yāodào diabolism</A>
</item>
<item id='_76'>
<cat>Most common Chinese characters 2092-2104 - Words</cat>
<Q>妖风</Q>
<A>traditional: 妖風&lt;br&gt;yāofēng evil wind</A>
</item>
<item id='_77'>
<cat>Most common Chinese characters 2092-2104 - Words</cat>
<Q>妖魔</Q>
<A>yāomó demon</A>
</item>
<item id='_78'>
<cat>Most common Chinese characters 2092-2104 - Words</cat>
<Q>剂量</Q>
<A>traditional: 劑量&lt;br&gt;jìliàng dosage; prescribed dose of medicine&lt;br&gt;jìliáng dose</A>
</item>
<item id='_79'>
<cat>Most common Chinese characters 2092-2104 - Words</cat>
<Q>吸收剂</Q>
<A>traditional: 吸收劑&lt;br&gt;xīshōujì absorbefacient</A>
</item>
<item id='_80'>
<cat>Most common Chinese characters 2092-2104 - Words</cat>
<Q>吸附剂</Q>
<A>traditional: 吸附劑&lt;br&gt;xīfùjì adsorbent</A>
</item>
<item id='_81'>
<cat>Most common Chinese characters 2092-2104 - Words</cat>
<Q>慢化剂</Q>
<A>traditional: 慢化劑&lt;br&gt;mànhuàjì moderator</A>
</item>
<item id='_82'>
<cat>Most common Chinese characters 2092-2104 - Words</cat>
<Q>指示剂</Q>
<A>traditional: 指示劑&lt;br&gt;zhǐshìjì indicator</A>
</item>
<item id='_83'>
<cat>Most common Chinese characters 2092-2104 - Words</cat>
<Q>减速剂</Q>
<A>traditional: 減速劑&lt;br&gt;jiǎnsùjì moderater</A>
</item>
<item id='_84'>
<cat>Most common Chinese characters 2092-2104 - Words</cat>
<Q>发泡剂</Q>
<A>traditional: 發泡劑&lt;br&gt;fāpāojì vesicant</A>
</item>
<item id='_85'>
<cat>Most common Chinese characters 2092-2104 - Words</cat>
<Q>药剂</Q>
<A>traditional: 藥劑&lt;br&gt;yàojì medicine</A>
</item>
<item id='_86'>
<cat>Most common Chinese characters 2092-2104 - Words</cat>
<Q>试剂</Q>
<A>traditional: 試劑&lt;br&gt;shìjì reagent</A>
</item>
<item id='_87'>
<cat>Most common Chinese characters 2092-2104 - Words</cat>
<Q>调剂</Q>
<A>traditional: 調劑&lt;br&gt;tiáojì (v) make an adjustment</A>
</item>
<item id='_88'>
<cat>Most common Chinese characters 2092-2104 - Words</cat>
<Q>还原剂</Q>
<A>traditional: 還原劑&lt;br&gt;huányuánjì reducing agent</A>
</item>
<item id='_89'>
<cat>Most common Chinese characters 2092-2104 - Words</cat>
<Q>防腐剂</Q>
<A>traditional: 防腐劑&lt;br&gt;fángfǔjì preservative</A>
</item>
<item id='_90'>
<cat>Most common Chinese characters 2092-2104 - Words</cat>
<Q>除草剂</Q>
<A>traditional: 除草劑&lt;br&gt;chúcǎojì (n) herbicide; weed killer</A>
</item>
<item id='_91'>
<cat>Most common Chinese characters 2092-2104 - Words</cat>
<Q>显影剂</Q>
<A>traditional: 顯影劑&lt;br&gt;xiǎnyǐngjì contrast medium</A>
</item>
<item id='_92'>
<cat>Most common Chinese characters 2092-2104 - Words</cat>
<Q>麻醉剂</Q>
<A>traditional: 麻醉劑&lt;br&gt;mázuìjì narcotic</A>
</item>
<item id='_93'>
<cat>Most common Chinese characters 2092-2104 - Words</cat>
<Q>广泛</Q>
<A>traditional: 廣泛&lt;br&gt;guǎngfàn extensive; wide range</A>
</item>
<item id='_94'>
<cat>Most common Chinese characters 2092-2104 - Words</cat>
<Q>泛滥</Q>
<A>traditional: 泛濫&lt;br&gt;fànlàn flooding</A>
</item>
<item id='_95'>
<cat>Most common Chinese characters 2092-2104 - Words</cat>
<Q>泛非主义</Q>
<A>traditional: 泛非主義&lt;br&gt;fánfēizhǔyì Pan-Africanism</A>
</item>
<item id='_96'>
<cat>Most common Chinese characters 2092-2104 - Words</cat>
<Q>泛音</Q>
<A>fànyīn overtone</A>
</item>
<item id='_97'>
<cat>Most common Chinese characters 2092-2104 - Words</cat>
<Q>布拉柴维尔</Q>
<A>traditional: 布拉柴維爾&lt;br&gt;bùlācháiwéiěr Brazzaville (capital of Congo)</A>
</item>
<item id='_98'>
<cat>Most common Chinese characters 2092-2104 - Words</cat>
<Q>柴油</Q>
<A>cháiyóu diesel fuel</A>
</item>
<item id='_99'>
<cat>Most common Chinese characters 2092-2104 - Words</cat>
<Q>柴油机</Q>
<A>traditional: 柴油機&lt;br&gt;cháiyóujī diesel engine</A>
</item>
<item id='_100'>
<cat>Most common Chinese characters 2092-2104 - Words</cat>
<Q>火柴</Q>
<A>huǒchái match</A>
</item>
<item id='_101'>
<cat>Most common Chinese characters 2092-2104 - Words</cat>
<Q>提携</Q>
<A>traditional: 提攜&lt;br&gt;tíxié to lead by the hand; to guide; to support</A>
</item>
<item id='_102'>
<cat>Most common Chinese characters 2092-2104 - Words</cat>
<Q>携带</Q>
<A>traditional: 攜帶&lt;br&gt;xiédài to carry; portable</A>
</item>
<item id='_103'>
<cat>Most common Chinese characters 2092-2104 - Words</cat>
<Q>携手</Q>
<A>traditional: 攜手&lt;br&gt;xiéshǒu to reach out</A>
</item>
</mnemosyne>
