<?xml version='1.0' encoding='UTF-8'?>
<mnemosyne core_version='1'>
<category active='1'>
<name>Most common Chinese characters 1166-1173 - English</name>
</category>
<category active='1'>
<name>Most common Chinese characters 1166-1173 - Hanzi</name>
</category>
<category active='1'>
<name>Most common Chinese characters 1166-1173 - Traditional</name>
</category>
<category active='1'>
<name>Most common Chinese characters 1166-1173 - Pinyin</name>
</category>
<category active='1'>
<name>Most common Chinese characters 1166-1173 - Words</name>
</category>
<item id='_0'>
<cat>Most common Chinese characters 1166-1173 - English</cat>
<Q>Write the character:&lt;br&gt;contemporaries; generation; lifetime</Q>
<A>辈 (strokes unavailable)&lt;br&gt;traditional: 輩&lt;br&gt;bèi&lt;br&gt;一辈子 (一輩子) yībèizi (for) a lifetime</A>
</item>
<item id='_1'>
<cat>Most common Chinese characters 1166-1173 - English</cat>
<Q>Write the character:&lt;br&gt;medicine</Q>
<A>&lt;img src="stroke-images/1167.png"&gt;&lt;br&gt;traditional: 藥&lt;br&gt;yào&lt;br&gt;药品 (藥品) yàopǐn medicaments; medicine; drug</A>
</item>
<item id='_2'>
<cat>Most common Chinese characters 1166-1173 - English</cat>
<Q>Write the character:&lt;br&gt;to cheat; to swindle; to deceive; to fool</Q>
<A>骗 (strokes unavailable)&lt;br&gt;traditional: 騙&lt;br&gt;piàn&lt;br&gt;欺骗 (欺騙) qīpiàn to deceive; to cheat</A>
</item>
<item id='_3'>
<cat>Most common Chinese characters 1166-1173 - English</cat>
<Q>Write the character:&lt;br&gt;green</Q>
<A>绿 (strokes unavailable)&lt;br&gt;traditional: 綠&lt;br&gt;lǜ&lt;br&gt;绿色 (綠色) lǜsè green</A>
</item>
<item id='_4'>
<cat>Most common Chinese characters 1166-1173 - English</cat>
<Q>Write the character:&lt;br&gt;surname Tong; boy; child; children</Q>
<A>童 (strokes unavailable)&lt;br&gt;tóng&lt;br&gt;儿童 (兒童) értóng child</A>
</item>
<item id='_5'>
<cat>Most common Chinese characters 1166-1173 - English</cat>
<Q>Write the character:&lt;br&gt;to withdraw; to pull back; to contract; to shrink; to reduce; abbreviation</Q>
<A>缩 (strokes unavailable)&lt;br&gt;traditional: 縮&lt;br&gt;suō&lt;br&gt;缩小 (縮小) suōxiǎo reduce; decrease</A>
</item>
<item id='_6'>
<cat>Most common Chinese characters 1166-1173 - English</cat>
<Q>Write the character:&lt;br&gt;mark; sign; talisman; to seal; to correspond to; tally; symbol; written charm; to coincide; surname Fu</Q>
<A>符 (strokes unavailable)&lt;br&gt;fú&lt;br&gt;符合 fúhé in keeping with; in accordance with; to agree with; to correspond with; to be in line with; manage; to handle</A>
</item>
<item id='_7'>
<cat>Most common Chinese characters 1166-1173 - English</cat>
<Q>Write the character:&lt;br&gt;to catch; to obtain; to capture</Q>
<A>&lt;img src="stroke-images/1173.png"&gt;&lt;br&gt;traditional: 獲&lt;br&gt;huò&lt;br&gt;获得 (獲得) huòdé to obtain; to receive; to get</A>
</item>
<item id='_8'>
<cat>Most common Chinese characters 1166-1173 - Hanzi</cat>
<Q>辈</Q>
<A>traditional: 輩&lt;br&gt;bèi&lt;br&gt;contemporaries; generation; lifetime&lt;br&gt;一辈子 (一輩子) yībèizi (for) a lifetime</A>
</item>
<item id='_9'>
<cat>Most common Chinese characters 1166-1173 - Hanzi</cat>
<Q>药</Q>
<A>traditional: 藥&lt;br&gt;yào&lt;br&gt;medicine&lt;br&gt;药品 (藥品) yàopǐn medicaments; medicine; drug</A>
</item>
<item id='_10'>
<cat>Most common Chinese characters 1166-1173 - Hanzi</cat>
<Q>骗</Q>
<A>traditional: 騙&lt;br&gt;piàn&lt;br&gt;to cheat; to swindle; to deceive; to fool&lt;br&gt;欺骗 (欺騙) qīpiàn to deceive; to cheat</A>
</item>
<item id='_11'>
<cat>Most common Chinese characters 1166-1173 - Hanzi</cat>
<Q>绿</Q>
<A>traditional: 綠&lt;br&gt;lǜ&lt;br&gt;green&lt;br&gt;绿色 (綠色) lǜsè green</A>
</item>
<item id='_12'>
<cat>Most common Chinese characters 1166-1173 - Hanzi</cat>
<Q>童</Q>
<A>tóng&lt;br&gt;surname Tong; boy; child; children&lt;br&gt;儿童 (兒童) értóng child</A>
</item>
<item id='_13'>
<cat>Most common Chinese characters 1166-1173 - Hanzi</cat>
<Q>缩</Q>
<A>traditional: 縮&lt;br&gt;suō&lt;br&gt;to withdraw; to pull back; to contract; to shrink; to reduce; abbreviation&lt;br&gt;缩小 (縮小) suōxiǎo reduce; decrease</A>
</item>
<item id='_14'>
<cat>Most common Chinese characters 1166-1173 - Hanzi</cat>
<Q>符</Q>
<A>fú&lt;br&gt;mark; sign; talisman; to seal; to correspond to; tally; symbol; written charm; to coincide; surname Fu&lt;br&gt;符合 fúhé in keeping with; in accordance with; to agree with; to correspond with; to be in line with; manage; to handle</A>
</item>
<item id='_15'>
<cat>Most common Chinese characters 1166-1173 - Hanzi</cat>
<Q>获</Q>
<A>traditional: 獲&lt;br&gt;huò&lt;br&gt;to catch; to obtain; to capture&lt;br&gt;获得 (獲得) huòdé to obtain; to receive; to get</A>
</item>
<item id='_16'>
<cat>Most common Chinese characters 1166-1173 - Traditional</cat>
<Q>輩</Q>
<A>simplified: 辈&lt;br&gt;bèi&lt;br&gt;contemporaries; generation; lifetime&lt;br&gt;一辈子 (一輩子) yībèizi (for) a lifetime</A>
</item>
<item id='_17'>
<cat>Most common Chinese characters 1166-1173 - Traditional</cat>
<Q>藥</Q>
<A>simplified: 药&lt;br&gt;yào&lt;br&gt;medicine&lt;br&gt;药品 (藥品) yàopǐn medicaments; medicine; drug</A>
</item>
<item id='_18'>
<cat>Most common Chinese characters 1166-1173 - Traditional</cat>
<Q>騙</Q>
<A>simplified: 骗&lt;br&gt;piàn&lt;br&gt;to cheat; to swindle; to deceive; to fool&lt;br&gt;欺骗 (欺騙) qīpiàn to deceive; to cheat</A>
</item>
<item id='_19'>
<cat>Most common Chinese characters 1166-1173 - Traditional</cat>
<Q>綠</Q>
<A>simplified: 绿&lt;br&gt;lǜ&lt;br&gt;green&lt;br&gt;绿色 (綠色) lǜsè green</A>
</item>
<item id='_20'>
<cat>Most common Chinese characters 1166-1173 - Traditional</cat>
<Q>縮</Q>
<A>simplified: 缩&lt;br&gt;suō&lt;br&gt;to withdraw; to pull back; to contract; to shrink; to reduce; abbreviation&lt;br&gt;缩小 (縮小) suōxiǎo reduce; decrease</A>
</item>
<item id='_21'>
<cat>Most common Chinese characters 1166-1173 - Traditional</cat>
<Q>獲</Q>
<A>simplified: 获&lt;br&gt;huò&lt;br&gt;to catch; to obtain; to capture&lt;br&gt;获得 (獲得) huòdé to obtain; to receive; to get</A>
</item>
<item id='_22'>
<cat>Most common Chinese characters 1166-1173 - Pinyin</cat>
<Q>Write the character: bèi&lt;br&gt;(yībèizi de bèi)</Q>
<A>辈 (strokes unavailable)&lt;br&gt;traditional: 輩&lt;br&gt;contemporaries; generation; lifetime&lt;br&gt;一辈子 (一輩子) yībèizi (for) a lifetime</A>
</item>
<item id='_23'>
<cat>Most common Chinese characters 1166-1173 - Pinyin</cat>
<Q>Write the character: yào&lt;br&gt;(yàopǐn de yào)</Q>
<A>&lt;img src="stroke-images/1167.png"&gt;&lt;br&gt;traditional: 藥&lt;br&gt;medicine&lt;br&gt;药品 (藥品) yàopǐn medicaments; medicine; drug</A>
</item>
<item id='_24'>
<cat>Most common Chinese characters 1166-1173 - Pinyin</cat>
<Q>Write the character: piàn&lt;br&gt;(qīpiàn de piàn)</Q>
<A>骗 (strokes unavailable)&lt;br&gt;traditional: 騙&lt;br&gt;to cheat; to swindle; to deceive; to fool&lt;br&gt;欺骗 (欺騙) qīpiàn to deceive; to cheat</A>
</item>
<item id='_25'>
<cat>Most common Chinese characters 1166-1173 - Pinyin</cat>
<Q>Write the character: lǜ&lt;br&gt;(lǜsè de lǜ)</Q>
<A>绿 (strokes unavailable)&lt;br&gt;traditional: 綠&lt;br&gt;green&lt;br&gt;绿色 (綠色) lǜsè green</A>
</item>
<item id='_26'>
<cat>Most common Chinese characters 1166-1173 - Pinyin</cat>
<Q>Write the character: tóng&lt;br&gt;(értóng de tóng)</Q>
<A>童 (strokes unavailable)&lt;br&gt;surname Tong; boy; child; children&lt;br&gt;儿童 (兒童) értóng child</A>
</item>
<item id='_27'>
<cat>Most common Chinese characters 1166-1173 - Pinyin</cat>
<Q>Write the character: suō&lt;br&gt;(suōxiǎo de suō)</Q>
<A>缩 (strokes unavailable)&lt;br&gt;traditional: 縮&lt;br&gt;to withdraw; to pull back; to contract; to shrink; to reduce; abbreviation&lt;br&gt;缩小 (縮小) suōxiǎo reduce; decrease</A>
</item>
<item id='_28'>
<cat>Most common Chinese characters 1166-1173 - Pinyin</cat>
<Q>Write the character: fú&lt;br&gt;(fúhé de fú)</Q>
<A>符 (strokes unavailable)&lt;br&gt;mark; sign; talisman; to seal; to correspond to; tally; symbol; written charm; to coincide; surname Fu&lt;br&gt;符合 fúhé in keeping with; in accordance with; to agree with; to correspond with; to be in line with; manage; to handle</A>
</item>
<item id='_29'>
<cat>Most common Chinese characters 1166-1173 - Pinyin</cat>
<Q>Write the character: huò&lt;br&gt;(huòdé de huò)</Q>
<A>&lt;img src="stroke-images/1173.png"&gt;&lt;br&gt;traditional: 獲&lt;br&gt;to catch; to obtain; to capture&lt;br&gt;获得 (獲得) huòdé to obtain; to receive; to get</A>
</item>
<item id='_30'>
<cat>Most common Chinese characters 1166-1173 - Words</cat>
<Q>一辈子</Q>
<A>traditional: 一輩子&lt;br&gt;yībèizi (for) a lifetime</A>
</item>
<item id='_31'>
<cat>Most common Chinese characters 1166-1173 - Words</cat>
<Q>前辈</Q>
<A>traditional: 前輩&lt;br&gt;qiánbèi senior; older generation</A>
</item>
<item id='_32'>
<cat>Most common Chinese characters 1166-1173 - Words</cat>
<Q>半辈子</Q>
<A>traditional: 半輩子&lt;br&gt;bànbèizi half of a lifetime</A>
</item>
<item id='_33'>
<cat>Most common Chinese characters 1166-1173 - Words</cat>
<Q>同辈</Q>
<A>traditional: 同輩&lt;br&gt;tóngbèi peer</A>
</item>
<item id='_34'>
<cat>Most common Chinese characters 1166-1173 - Words</cat>
<Q>后辈</Q>
<A>traditional: 後輩&lt;br&gt;hòubèi younger generation</A>
</item>
<item id='_35'>
<cat>Most common Chinese characters 1166-1173 - Words</cat>
<Q>老一辈</Q>
<A>traditional: 老一輩&lt;br&gt;lǎoyībèi older generation</A>
</item>
<item id='_36'>
<cat>Most common Chinese characters 1166-1173 - Words</cat>
<Q>老前辈</Q>
<A>traditional: 老前輩&lt;br&gt;lǎoqiánbèi old-timer</A>
</item>
<item id='_37'>
<cat>Most common Chinese characters 1166-1173 - Words</cat>
<Q>辈出</Q>
<A>traditional: 輩出&lt;br&gt;bèichū come forth in large numbers</A>
</item>
<item id='_38'>
<cat>Most common Chinese characters 1166-1173 - Words</cat>
<Q>辈分</Q>
<A>traditional: 輩分&lt;br&gt;bèifèn seniority in the family or clan; position in the family hierarchy</A>
</item>
<item id='_39'>
<cat>Most common Chinese characters 1166-1173 - Words</cat>
<Q>辈子</Q>
<A>traditional: 輩子&lt;br&gt;bèizi all one's life; lifetime</A>
</item>
<item id='_40'>
<cat>Most common Chinese characters 1166-1173 - Words</cat>
<Q>长辈</Q>
<A>traditional: 長輩&lt;br&gt;zhǎngbèi elder generation</A>
</item>
<item id='_41'>
<cat>Most common Chinese characters 1166-1173 - Words</cat>
<Q>中草药</Q>
<A>traditional: 中草藥&lt;br&gt;zhōngcǎoyào Chinese herbal medicine</A>
</item>
<item id='_42'>
<cat>Most common Chinese characters 1166-1173 - Words</cat>
<Q>中药</Q>
<A>traditional: 中藥&lt;br&gt;Zhōngyào (traditional) Chinese medicine&lt;br&gt;zhōngyào traditional Chinese medicine</A>
</item>
<item id='_43'>
<cat>Most common Chinese characters 1166-1173 - Words</cat>
<Q>山药</Q>
<A>traditional: 山藥&lt;br&gt;shānyao Dioscorea opposita; yam</A>
</item>
<item id='_44'>
<cat>Most common Chinese characters 1166-1173 - Words</cat>
<Q>弹药</Q>
<A>traditional: 彈藥&lt;br&gt;dànyào ammunition</A>
</item>
<item id='_45'>
<cat>Most common Chinese characters 1166-1173 - Words</cat>
<Q>成药</Q>
<A>traditional: 成藥&lt;br&gt;chéngyào (n) officinal; patent medicine</A>
</item>
<item id='_46'>
<cat>Most common Chinese characters 1166-1173 - Words</cat>
<Q>毒药</Q>
<A>traditional: 毒藥&lt;br&gt;dúyào poison</A>
</item>
<item id='_47'>
<cat>Most common Chinese characters 1166-1173 - Words</cat>
<Q>火药</Q>
<A>traditional: 火藥&lt;br&gt;huǒyào gunpowder</A>
</item>
<item id='_48'>
<cat>Most common Chinese characters 1166-1173 - Words</cat>
<Q>花药</Q>
<A>traditional: 花藥&lt;br&gt;huāyào anther</A>
</item>
<item id='_49'>
<cat>Most common Chinese characters 1166-1173 - Words</cat>
<Q>草药</Q>
<A>traditional: 草藥&lt;br&gt;cǎoyào herbal medicine</A>
</item>
<item id='_50'>
<cat>Most common Chinese characters 1166-1173 - Words</cat>
<Q>药品</Q>
<A>traditional: 藥品&lt;br&gt;yàopǐn medicaments; medicine; drug</A>
</item>
<item id='_51'>
<cat>Most common Chinese characters 1166-1173 - Words</cat>
<Q>药房</Q>
<A>traditional: 藥房&lt;br&gt;yàofáng pharmacy; drugstore</A>
</item>
<item id='_52'>
<cat>Most common Chinese characters 1166-1173 - Words</cat>
<Q>药方</Q>
<A>traditional: 藥方&lt;br&gt;yàofāng prescription</A>
</item>
<item id='_53'>
<cat>Most common Chinese characters 1166-1173 - Words</cat>
<Q>药材</Q>
<A>traditional: 藥材&lt;br&gt;yàocái drug ingredients</A>
</item>
<item id='_54'>
<cat>Most common Chinese characters 1166-1173 - Words</cat>
<Q>药水</Q>
<A>traditional: 藥水&lt;br&gt;yàoshuǐ liquid medicine; lotion</A>
</item>
<item id='_55'>
<cat>Most common Chinese characters 1166-1173 - Words</cat>
<Q>药物</Q>
<A>traditional: 藥物&lt;br&gt;yàowù medicaments; pharmaceuticals; medication; medicine; drug</A>
</item>
<item id='_56'>
<cat>Most common Chinese characters 1166-1173 - Words</cat>
<Q>医药</Q>
<A>traditional: 醫藥&lt;br&gt;yīyào medicine</A>
</item>
<item id='_57'>
<cat>Most common Chinese characters 1166-1173 - Words</cat>
<Q>麻药</Q>
<A>traditional: 麻藥&lt;br&gt;máyào anesthetic</A>
</item>
<item id='_58'>
<cat>Most common Chinese characters 1166-1173 - Words</cat>
<Q>受骗</Q>
<A>traditional: 受騙&lt;br&gt;shòupiàn cheated; taken in; hoodwinked</A>
</item>
<item id='_59'>
<cat>Most common Chinese characters 1166-1173 - Words</cat>
<Q>骗人</Q>
<A>traditional: 騙人&lt;br&gt;piànrén to cheat sb; a scam</A>
</item>
<item id='_60'>
<cat>Most common Chinese characters 1166-1173 - Words</cat>
<Q>骗取</Q>
<A>traditional: 騙取&lt;br&gt;piànqǔ to gain by cheating</A>
</item>
<item id='_61'>
<cat>Most common Chinese characters 1166-1173 - Words</cat>
<Q>骗子</Q>
<A>traditional: 騙子&lt;br&gt;piànzi swindler; a cheat</A>
</item>
<item id='_62'>
<cat>Most common Chinese characters 1166-1173 - Words</cat>
<Q>骗局</Q>
<A>traditional: 騙局&lt;br&gt;piànjú a swindle; a trap; a racket; a scam</A>
</item>
<item id='_63'>
<cat>Most common Chinese characters 1166-1173 - Words</cat>
<Q>骗术</Q>
<A>traditional: 騙術&lt;br&gt;piànshù trick; deceit</A>
</item>
<item id='_64'>
<cat>Most common Chinese characters 1166-1173 - Words</cat>
<Q>绿化</Q>
<A>traditional: 綠化&lt;br&gt;lǜhuà to make green with plants; to reforest</A>
</item>
<item id='_65'>
<cat>Most common Chinese characters 1166-1173 - Words</cat>
<Q>绿林</Q>
<A>traditional: 綠林&lt;br&gt;lǜlín green wood; place name in Hubei, the starting point for a major rebellion at the end of Western Han</A>
</item>
<item id='_66'>
<cat>Most common Chinese characters 1166-1173 - Words</cat>
<Q>绿洲</Q>
<A>traditional: 綠洲&lt;br&gt;lǜzhōu oasis</A>
</item>
<item id='_67'>
<cat>Most common Chinese characters 1166-1173 - Words</cat>
<Q>绿灯</Q>
<A>traditional: 綠燈&lt;br&gt;lǜdēng green light</A>
</item>
<item id='_68'>
<cat>Most common Chinese characters 1166-1173 - Words</cat>
<Q>绿营</Q>
<A>traditional: 綠營&lt;br&gt;lǜyíng Green Standard Army</A>
</item>
<item id='_69'>
<cat>Most common Chinese characters 1166-1173 - Words</cat>
<Q>绿色</Q>
<A>traditional: 綠色&lt;br&gt;lǜsè green</A>
</item>
<item id='_70'>
<cat>Most common Chinese characters 1166-1173 - Words</cat>
<Q>绿叶</Q>
<A>traditional: 綠葉&lt;br&gt;lùyè greenery</A>
</item>
<item id='_71'>
<cat>Most common Chinese characters 1166-1173 - Words</cat>
<Q>叶绿素</Q>
<A>traditional: 葉綠素&lt;br&gt;yèlùsù chlorophyll&lt;br&gt;yèlǜsù chlorophyll</A>
</item>
<item id='_72'>
<cat>Most common Chinese characters 1166-1173 - Words</cat>
<Q>叶绿体</Q>
<A>traditional: 葉綠體&lt;br&gt;yèlùtī chloroplast&lt;br&gt;yèlǜtǐ chloroplast</A>
</item>
<item id='_73'>
<cat>Most common Chinese characters 1166-1173 - Words</cat>
<Q>儿童</Q>
<A>traditional: 兒童&lt;br&gt;értóng child</A>
</item>
<item id='_74'>
<cat>Most common Chinese characters 1166-1173 - Words</cat>
<Q>儿童心理学</Q>
<A>traditional: 兒童心理學&lt;br&gt;értóngxīnlǐxué kidology</A>
</item>
<item id='_75'>
<cat>Most common Chinese characters 1166-1173 - Words</cat>
<Q>神童</Q>
<A>shéntóng (n) child prodigy</A>
</item>
<item id='_76'>
<cat>Most common Chinese characters 1166-1173 - Words</cat>
<Q>童工</Q>
<A>tónggōng child labor</A>
</item>
<item id='_77'>
<cat>Most common Chinese characters 1166-1173 - Words</cat>
<Q>童年</Q>
<A>tóngnián childhood</A>
</item>
<item id='_78'>
<cat>Most common Chinese characters 1166-1173 - Words</cat>
<Q>童话</Q>
<A>traditional: 童話&lt;br&gt;tónghuà children's fairy tales</A>
</item>
<item id='_79'>
<cat>Most common Chinese characters 1166-1173 - Words</cat>
<Q>压缩</Q>
<A>traditional: 壓縮&lt;br&gt;yāsuō to compress; compression</A>
</item>
<item id='_80'>
<cat>Most common Chinese characters 1166-1173 - Words</cat>
<Q>压缩机</Q>
<A>traditional: 壓縮機&lt;br&gt;yāsùjī (n) compactor; compressor</A>
</item>
<item id='_81'>
<cat>Most common Chinese characters 1166-1173 - Words</cat>
<Q>压缩比</Q>
<A>traditional: 壓縮比&lt;br&gt;yāsuōbǐ compression ratio</A>
</item>
<item id='_82'>
<cat>Most common Chinese characters 1166-1173 - Words</cat>
<Q>收缩</Q>
<A>traditional: 收縮&lt;br&gt;shōusuō pull back; shrink; contract</A>
</item>
<item id='_83'>
<cat>Most common Chinese characters 1166-1173 - Words</cat>
<Q>紧缩</Q>
<A>traditional: 緊縮&lt;br&gt;jǐnsuō reduce; tighten; cut back (budget etc)</A>
</item>
<item id='_84'>
<cat>Most common Chinese characters 1166-1173 - Words</cat>
<Q>缩写</Q>
<A>traditional: 縮寫&lt;br&gt;suōxiě abbreviation; to abridge</A>
</item>
<item id='_85'>
<cat>Most common Chinese characters 1166-1173 - Words</cat>
<Q>缩小</Q>
<A>traditional: 縮小&lt;br&gt;suōxiǎo reduce; decrease</A>
</item>
<item id='_86'>
<cat>Most common Chinese characters 1166-1173 - Words</cat>
<Q>缩影</Q>
<A>traditional: 縮影&lt;br&gt;suōyǐng miniature; a big picture in a nutshell; the epitome (of sth)</A>
</item>
<item id='_87'>
<cat>Most common Chinese characters 1166-1173 - Words</cat>
<Q>缩水</Q>
<A>traditional: 縮水&lt;br&gt;suōshuǐ shrink</A>
</item>
<item id='_88'>
<cat>Most common Chinese characters 1166-1173 - Words</cat>
<Q>缩减</Q>
<A>traditional: 縮減&lt;br&gt;suōjiǎn to cut; to reduce</A>
</item>
<item id='_89'>
<cat>Most common Chinese characters 1166-1173 - Words</cat>
<Q>缩短</Q>
<A>traditional: 縮短&lt;br&gt;suōduǎn to curtail; to cut down</A>
</item>
<item id='_90'>
<cat>Most common Chinese characters 1166-1173 - Words</cat>
<Q>退缩</Q>
<A>traditional: 退縮&lt;br&gt;tuìsuō to shrink back; to cower&lt;br&gt;tuìsù balk</A>
</item>
<item id='_91'>
<cat>Most common Chinese characters 1166-1173 - Words</cat>
<Q>不符</Q>
<A>bùfú inconsistent; not in agreement with; not agree or tally with; not conform to</A>
</item>
<item id='_92'>
<cat>Most common Chinese characters 1166-1173 - Words</cat>
<Q>休止符</Q>
<A>xiūzhǐfú rest (music)</A>
</item>
<item id='_93'>
<cat>Most common Chinese characters 1166-1173 - Words</cat>
<Q>八分音符</Q>
<A>bāfēnyīnfú quaver; eighth note</A>
</item>
<item id='_94'>
<cat>Most common Chinese characters 1166-1173 - Words</cat>
<Q>十六分音符</Q>
<A>shíliùfēnyīnfú semiquaver</A>
</item>
<item id='_95'>
<cat>Most common Chinese characters 1166-1173 - Words</cat>
<Q>字符</Q>
<A>zìfú word-symbol; character</A>
</item>
<item id='_96'>
<cat>Most common Chinese characters 1166-1173 - Words</cat>
<Q>相符</Q>
<A>xiāngfú (v) match up to; tally</A>
</item>
<item id='_97'>
<cat>Most common Chinese characters 1166-1173 - Words</cat>
<Q>符合</Q>
<A>fúhé in keeping with; in accordance with; to agree with; to correspond with; to be in line with; manage; to handle</A>
</item>
<item id='_98'>
<cat>Most common Chinese characters 1166-1173 - Words</cat>
<Q>符号</Q>
<A>traditional: 符號&lt;br&gt;fúhào symbol; mark; sign</A>
</item>
<item id='_99'>
<cat>Most common Chinese characters 1166-1173 - Words</cat>
<Q>音符</Q>
<A>yīnfú (music) note; phonetic component of a Chinese character; phonetic symbol; phonogram</A>
</item>
<item id='_100'>
<cat>Most common Chinese characters 1166-1173 - Words</cat>
<Q>收获</Q>
<A>traditional: 收獲&lt;br&gt;shōuhuò benefit, reward</A>
</item>
<item id='_101'>
<cat>Most common Chinese characters 1166-1173 - Words</cat>
<Q>查获</Q>
<A>traditional: 查獲&lt;br&gt;cháhuò (v) investigate and capture a criminal</A>
</item>
<item id='_102'>
<cat>Most common Chinese characters 1166-1173 - Words</cat>
<Q>荣获</Q>
<A>traditional: 榮獲&lt;br&gt;rónghuò be honored with</A>
</item>
<item id='_103'>
<cat>Most common Chinese characters 1166-1173 - Words</cat>
<Q>获胜</Q>
<A>traditional: 獲勝&lt;br&gt;huòshèng be victorious</A>
</item>
<item id='_104'>
<cat>Most common Chinese characters 1166-1173 - Words</cat>
<Q>获取</Q>
<A>traditional: 獲取&lt;br&gt;huòqǔ to gain; to get; to acquire</A>
</item>
<item id='_105'>
<cat>Most common Chinese characters 1166-1173 - Words</cat>
<Q>获得</Q>
<A>traditional: 獲得&lt;br&gt;huòdé to obtain; to receive; to get</A>
</item>
<item id='_106'>
<cat>Most common Chinese characters 1166-1173 - Words</cat>
<Q>破获</Q>
<A>traditional: 破獲&lt;br&gt;pòhuò to uncover (a criminal plot); to break open and capture</A>
</item>
</mnemosyne>
